Workbook

Sheet Raw_Transcripts
A1: participant_id | B1: start | C1: end | D1: text | E1: speaker | F1: source_type | G1: main_phase | H1: sub_phase | I1: deductive_code | J1: quotes | K1: inductive_codes
A2: 1 | B2: 1029 | C2: 9370 | D2: Ja, dann nochmal danke dir, dass du dir die Zeit genommen hast und die Nutzerstudie dauert | E2: Speaker 2 | G2: General
A3: 1 | B3: 9370 | C3: 16450 | D3: so ungefähr 45 bis 60 Minuten, das Interview wird mit der Software OBS aufgezeichnet, um | E3: Speaker 2
A4: 1 | B4: 16450 | C4: 22550 | D4: das dann später zu transkribieren und die Audio wird dann nach der Transkription gelöfft | E4: Speaker 2
A5: 1 | B5: 22550 | C5: 28670 | D5: und du kannst auch während des Interviews immer stoppen und deine Einwilligungen zurückziehen | E5: Speaker 2
A6: 1 | B6: 28670 | C6: 35210 | D6: ohne irgendwelche Gründe zu benennen oder negative Folgen davon zu bekommen und deswegen | E6: Speaker 2
A7: 1 | B7: 35210 | C7: 38090 | D7: einmal die Frage, ob du damit einverstanden bist, dass ich das aufzeichne? | E7: Speaker 2
A8: 1 | B8: 39390 | C8: 39550 | D8: Ja. | E8: Speaker 2
A9: 1 | B9: 40250 | C9: 41070 | D9: Okay, perfekt. | E9: Speaker 2
A10: 1 | B10: 42690 | C10: 50650 | D10: Und genau, dann einmal zur Struktur, also du hast ja schon den Link bekommen zu der App | E10: Speaker 2
A11: 1 | B11: 51530 | C11: 57910 | D11: und das sieht wie folgendermaßen aus, die Nutzerstudie, zuerst musst du ein kleines Onboarding | E11: Speaker 2
A12: 1 | B12: 57910 | C12: 65030 | D12: machen, um ein paar Fragen zu beantworten, dann hast du eine Konversation als Warm-up | E12: Speaker 2
A13: 1 | B13: 65030 | C13: 70770 | D13: und dann zwei weitere Konversationen und nach jeder Konversation hast du nochmal so eine | E13: Speaker 2
A14: 1 | B14: 70770 | C14: 77710 | D14: kurze Übersicht, so eine Art Summary, die du dann auf deinem Bildschirm siehst, die | E14: Speaker 2
... A28: 1 | B28: 244530 | C28: 244870 | D28: Okay. | E28: Speaker 1
A29: 1 | B29: 247190 | C29: 252470 | D29: Ja, ich glaube, die Language-Level hier sind relativ übersichtlich, da bin ich auf jeden Fall hier. | E29: Speaker 1 | I29: GEN_UI_UX
A30: 1 | B30: 255730 | C30: 258329 | D30: Ich schreibe so ein bisschen mit, wenn nicht, dass du dich wunderst. | E30: Speaker 2
A31: 1 | B31: 259630 | C31: 263250 | D31: Ja, meine Muttersprache ist Deutsch. | E31: Speaker 1
A32: 1 | B32: 263250 | C32: 266610 | D32: Ah, ich kann nur eine auswählen, okay. | E32: Speaker 1
A33: 1 | B33: 268730 | C33: 271330 | D33: Aber ist bei mir auch richtig mit einer Muttersprache? | E33: Speaker 1
A34: 1 | B34: 279480 | C34: 286180 | D34: Do you struggle with up to five? | E34: Speaker 1
A35: 1 | B35: 286360 | C35: 286560 | D35: Okay. | E35: Speaker 1
A36: 1 | B36: 289830 | C36: 295250 | D36: Boah, ja, die Gendern im Spanischen kann ich mir nicht so merken. | E36: Speaker 1
A37: 1 | B37: 296710 | C37: 298050 | D37: Mathikregeln auch noch schwierig. | E37: Speaker 1
A38: 1 | B38: 300770 | C38: 314520 | D38: Die Frage ist, gehe ich jetzt eher auf die Sachen, die halt so ganz schwer sind, oder so Sachen, mit denen ich auch noch struggle. | E38: Speaker 1
A39: 1 | B39: 315240 | C39: 317980 | D39: Eigentlich bin ich gerade eher, glaube ich, mir am vieren abwählen. | E39: Speaker 1
A40: 1 | B40: 321980 | C40: 324620 | D40: Ja, four-leaf-speaking ist reine Kopfsache. | E40: Speaker 1
A41: 1 | B41: 325660 | C41: 327440 | D41: Ja, konjugieren ist immer ein bisschen schwierig. | E41: Speaker 1
... A66: 1 | B66: 531250 | C66: 533550 | D66: Das sollte vielleicht nicht mal beim selben rauskommen. | E66: Speaker 1
A67: 1 | B67: 539500 | C67: 541360 | D67: Sieht lustig aus. | E67: Speaker 2 | I67: CUST_Partner
A68: 1 | B68: 542060 | C68: 544460 | D68: Du musst nach oben den Namen eingeben. | E68: Speaker 2
A69: 1 | B69: 545200 | C69: 546640 | D69: Oh, ich muss den Namen eingeben, ja. | E69: Speaker 2
A70: 1 | B70: 548860 | C70: 551640 | D70: Stimmt, wer nicht blind ist. | E70: Speaker 1
A71: 1 | B71: 556650 | C71: 561750 | D71: Wenn ich mich jetzt schon einmal Frucht benannt habe, dann kriegt ihr jetzt auch einen Fruchtnamen. | E71: Speaker 1
A72: 1 | B72: 564330 | C72: 567390 | D72: Okay, also ich vermute, das ist jetzt das erste Szenario. | E72: Speaker 1
A73: 1 | B73: 572250 | C73: 574250 | D73: Okay, dann Generate Task. | E73: Speaker 1
A74: 1 | B74: 574490 | C74: 576250 | D74: Klingt so, als müsste ich jetzt ein paar Aufgaben. | E74: Speaker 2
A75: 1 | B75: 576250 | C75: 578530 | D75: Genau, bevor du weitergehst. | E75: Speaker 2
A76: 1 | B76: 579030 | C76: 584190 | D76: Auch wichtig, jedes Szenario oder jeder Chat hat ein Limit. | E76: Speaker 2
A77: 1 | B77: 584450 | C77: 587210 | D77: Also man kann maximal 15 Nachrichten schreiben. | E77: Speaker 2
A78: 1 | B78: 588790 | C78: 591410 | D78: Also 15 Nachrichten jeder. | E78: Speaker 2
A79: 1 | B79: 593470 | C79: 603210 | D79: Aber das Limit ist trotzdem hochgesetzt, damit auch angeregt wird, dass man eine Konversation hat und nicht nur versucht, die Aufgaben zu lösen. | E79: Speaker 2
... A114: 1 | B114: 743700 | C114: 744020 | D114: Ähm. | E114: Speaker 1
A115: 1 | B115: 746730 | C115: 748990 | D115: Schon mal sehr angenehm, diesen Sprachknopf zu haben. | E115: Speaker 1 | I115: GEN_UI_UX
A116: 1 | B116: 749090 | C116: 754130 | D116: Da muss man sicherlich die ganze Zeit ruhig sein, bis man irgendwie eine Idee hat. | E116: Speaker 1
A117: 1 | B117: 755230 | C117: 757210 | D117: Okay, ich glaube, ich verstehe einigermaßen. | E117: Speaker 1
A118: 1 | B118: 757310 | C118: 758770 | D118: Das ist ja, glaube ich, nicht ganz alles. | E118: Speaker 1
A119: 1 | B119: 759690 | C119: 761770 | D119: Hola, me llamo Orange. | E119: Speaker 1
A120: 1 | B120: 762990 | C120: 767600 | D120: Es ist auch trocken. | E120: Speaker 1
A121: 1 | B121: 770370 | C121: 771590 | D121: Te sientes? | E121: Speaker 1
A122: 1 | B122: 773190 | C122: 773290 | D122: Ähm. | E122: Speaker 1
A123: 1 | B123: 774070 | C123: 774370 | D123: Hm. | E123: Speaker 1
A124: 1 | B124: 777400 | C124: 778840 | D124: Jetzt stecke ich ein bisschen fest. | E124: Speaker 1
A125: 1 | B125: 779300 | C125: 779840 | D125: Was macht das? | E125: Speaker 1
A126: 1 | B126: 780000 | C126: 781220 | D126: Ah, da könnte ich es tippen. | E126: Speaker 1
A127: 1 | B127: 785190 | C127: 786810 | D127: Our personalization. | E127: Speaker 1
... A180: 1 | B180: 1006260 | C180: 1008740 | D180: Verstehe ich meistens dann einen Satz oder so wie. | E180: Speaker 1
A181: 1 | B181: 1008900 | C181: 1011660 | D181: Aber ich traue mich nicht so ganz, die KI zu fragen. Ob sie nochmal den zweiten oder dritten erklären kann. Deswegen frage ich einfach, ob sie alles erklärt. Wie meinst du das genau? Ich hab manchmal irgendwie den Eindruck. Weil so. KI. Wenn man dann. Mit denen redet. Dass sie. Wenn man dann so sagt. Erklär mal den zweiten Satz. Dass sie sich dann vorzählen. Und den dritten erklären. Oder irgendwie so. | E181: Speaker 1 | J181: QUOTE
A182: 1 | B182: 1036609 | C182: 1036790 | D182: Hm. | E182: Speaker 2
A183: 1 | B183: 1037470 | C183: 1037869 | D183: Ähm. | E183: Speaker 1
A184: 1 | B184: 1042240 | C184: 1042599 | D184: Okay. | E184: Speaker 1
A185: 1 | B185: 1043160 | C185: 1046000 | D185: Die Formatierung kapiere ich jetzt nicht ganz. | E185: Speaker 1
A186: 1 | B186: 1047060 | C186: 1047339 | D186: Ah. | E186: Speaker 1
A187: 1 | B187: 1047440 | C187: 1049980 | D187: Das erklärt mir hier, wie es formatiert ist. | E187: Speaker 1
A188: 1 | B188: 1051820 | C188: 1053000 | D188: Spanish, English, Note. | E188: Speaker 1
A189: 1 | B189: 1053140 | C189: 1053240 | D189: Oder? | E189: Speaker 1
A190: 1 | B190: 1054720 | C190: 1055120 | D190: Genau. | E190: Speaker 2
A191: 1 | B191: 1055340 | C191: 1056420 | D191: Ich glaube. | E191: Speaker 1
A192: 1 | B192: 1056880 | C192: 1057180 | D192: Spanish, English, Note. | E192: Speaker 2
A193: 1 | B193: 1057180 | C193: 1057860 | D193: Ah. | E193: Speaker 2
... A221: 1 | B221: 1117850 | C221: 1119230 | D221: Dann kopiere ich die doch einfach. Ich schreibe mal noch bitte mit rein. Dann wird die Antwort vielleicht besser. | E221: Speaker 1
A222: 1 | B222: 1173790 | C222: 1175110 | D222: Das mit dem Tutor ist schon gut. | E222: Speaker 1 | I222: UX_Efficiency | J222: QUOTE
A223: 1 | B223: 1175850 | C223: 1176070 | D223: Ah. | E223: Speaker 1
A224: 1 | B224: 1176110 | C224: 1177250 | D224: Jetzt kommt wieder die Ansicht. | E224: Speaker 1
A225: 1 | B225: 1177710 | C225: 1179210 | D225: Die mir vorher auch gut gefallen. | E225: Speaker 1
A226: 1 | B226: 1180590 | C226: 1181190 | D226: Ähm. | E226: Speaker 1
A227: 1 | B227: 1187560 | C227: 1188420 | D227: Du bist doll. | E227: Speaker 1
A228: 1 | B228: 1190520 | C228: 1191120 | D228: Muy contento. | E228: Speaker 1
A229: 1 | B229: 1191900 | C229: 1192300 | D229: Ah. | E229: Speaker 1
A230: 1 | B230: 1192580 | C230: 1192680 | D230: Ja. | E230: Speaker 1
A231: 1 | B231: 1192940 | C231: 1193120 | D231: Ja. | E231: Speaker 1
A232: 1 | B232: 1193200 | C232: 1193440 | D232: Okay. | E232: Speaker 1
A233: 1 | B233: 1193620 | C233: 1193820 | D233: Okay. | E233: Speaker 1
A234: 1 | B234: 1194940 | C234: 1195540 | D234: Verstehe. | E234: Speaker 1
... A277: 1 | B277: 1315690 | C277: 1316410 | D277: Me alegro. | E277: Speaker 1
A278: 1 | B278: 1317390 | C278: 1318510 | D278: Jetzt steht hier reconnecting. | E278: Speaker 1 | I278: UX_Frustration
A279: 1 | B279: 1322180 | C279: 1322660 | D279: Okay. | E279: Speaker 1
A280: 1 | B280: 1322720 | C280: 1324140 | D280: Ich kann alles klicken. | E280: Speaker 2
A281: 1 | B281: 1327020 | C281: 1329300 | D281: Es kann irgendwas mit dem Internet vielleicht. | E281: Speaker 2
A282: 1 | B282: 1329300 | C282: 1334180 | D282: Weil eigentlich sollte es funktionieren. | E282: Speaker 2
A283: 1 | B283: 1335460 | C283: 1336660 | D283: Das könnte es sein. | E283: Speaker 1
A284: 1 | B284: 1336900 | C284: 1337400 | D284: Also ich hab. | E284: Speaker 1
A285: 1 | B285: 1337860 | C285: 1338820 | D285: Also dich höre ich ja noch. | E285: Speaker 1
A286: 1 | B286: 1339060 | C286: 1339440 | D286: Deswegen. | E286: Speaker 1
A287: 1 | B287: 1341980 | C287: 1345080 | D287: Soll ich irgendwie was testen? | E287: Speaker 1
A288: 1 | B288: 1345280 | C288: 1345880 | D288: Warte mal. | E288: Speaker 1
A289: 1 | B289: 1346300 | C289: 1349360 | D289: Sonst wenn du mal diese Konsole aufmachst. | E289: Speaker 2
A290: 1 | B290: 1350380 | C290: 1351000 | D290: Ja. | E290: Speaker 2
... A886: 1 | B886: 7575360 | C886: 7580380 | D886: Dann danke dir auf jeden Fall für deine Teilnahme und dann beende ich einmal die Aufnahme. | E886: Speaker 2
A887: 1 | B887: 0 | C887: 0 | D887: Language level are clean | E887: Speaker 1 | F887: Observation Note | G887: Pre-Phase / General
...

Sheet Code List
A1: RQs | B1: Category | C1: Code | D1: Description
A2: RQ1 - UX | B2: UX (User Experience) | C2: UX_Emotion | D2: Statements regarding the emotional state, enjoyment, and hedonic quality of the interaction.
C3: UX_Efficiency | D3: Perceived efficiency, smoothness, and goal-attainment speed during the conversation.
C4: UX_Frustration | D4: Mentions of confusion, cognitive overload, or moments where the system blocked the user's progress.
C5: UX_UsageIntention | D5: Explicit statements about the intention to use the system for future language practice outside the study.
A6: RQ1 - Personalization | B6: PER (Personalization) | C6: PER_Adaption | D6: The user's general awareness or failure to notice the customized elements within the prompt.
C7: PER_Level | D7: Perception of how well the system's vocabulary and complexity matched the user's A1-A2 proficiency.
C8: PER_TaskAdaption | D8: How dynamically the partner reacted to the user's specific conversational inputs and roleplay attempts.
C9: PER_MistakeHandling | D9: Feedback on how the system addressed, corrected, or ignored language mistakes and struggles.
A10: RQ2 - Learning Outcomes | B10: LEARN (Perceived Learning) | C10: LEARN_Productivity | D10: The perceived impact of the conversation on the user's specific language learning goals.
C11: LEARN_Confidence | D11: The effect of the interaction on the user's confidence and willingness to speak freely.
A12: RQ3 - Customization | B12: CUST (Customization) | C12: CUST_Partner | D12: Statements regarding the customized partner.
C13: CUST_Motivation | D13: Reasons and motivations behind the specific choices made during the avatar and profile setup.
C14: CUST_Rating | D14: Evaluation and feedback regarding the available onboarding options (e.g., hobbies, interests).
C15: CUST_Missing | D15: Explicit requests for additional customization features that were not present in the current system.
B16: COMP / GEN (Comparisons) | C16: COMP_Preference | D16: The overarching preference for either Chat 1 or Chat 2 and the main rationale behind it.
C17: COMP_Variant | D17: The user's guess regarding which conversation utilized the personalized LLM prompt.
C18: GEN_Improvement | D18: General ideas, feature requests, and suggestions to improve the application.
C19: GEN_UI_UX | D19: Researcher notes on general interface issues, bugs, or UI/UX problems not related to the LLM prompt.
B20: OBS (Observations) | C20: OBS_UserBehavior | D20: Researcher notes on actual system usage, task performance, and hint reliance during the session.
B21: CONF (Confounders) | C21: CONF_Scenario | D21: Bias introduced by the user's personal preference for the conversational setting (e.g., Cafe vs. Market).
C22: CONF_TaskPerformance | D22: Methodological artifacts where a lack of user errors prevented the system from delivering personalized feedback.
C23: CONF_Timeframe | D23: Limitations arising from the short study duration preventing the establishment of a deeper user-AI relationship.
C24: CONF_Others | D24: Confounding variables different to the three above.

Sheet Phases
A1: Onboarding
A2: Warmup
A3: Chat 1
A4: Chat 2
A5: Summary
A6: Evaluation
A7: General

Sheet comparative_sys_preference
A1: pid | B1: group | C1: overall_preference | D1: ref | E1: more_efficient | F1: ref | G1: less_frustrating | H1: ref | I1: more_productive | J1: ref | K1: more_confident | L1: ref | M1: more_level_adapted | N1: ref | O1: more_task_adapted | P1: ref | Q1: better_mistake_handling | R1: ref | S1: experiment_guess | T1: ref
A2: 1 | B2: =_xlfn.XLOOKUP(A2,participants!A:A,participants!C:C) -> control_first | C2: experiment | D2: =ROW(Cleaned_Transcripts!E585) -> 585 | E2: control | F2: =ROW(Cleaned_Transcripts!E631) -> 631 | G2: experiment | H2: =ROW(Cleaned_Transcripts!E651) -> 651 | I2: experiment | J2: =ROW(Cleaned_Transcripts!E656) -> 656 | K2: experiment | L2: =ROW(Cleaned_Transcripts!E659) -> 659 | M2: experiment | N2: =ROW(Cleaned_Transcripts!E664) -> 664 | O2: neutral | P2: =ROW(Cleaned_Transcripts!E672) -> 672 | Q2: experiment | R2: =ROW(Cleaned_Transcripts!E681) -> 681 | S2: experiment | T2: =ROW(Cleaned_Transcripts!E735) -> 735
A3: 2 | B3: =_xlfn.XLOOKUP(A3,participants!A:A,participants!C:C) -> experiment_first | C3: experiment | D3: =ROW(Cleaned_Transcripts!E1326) -> 1326 | E3: experiment | F3: =ROW(Cleaned_Transcripts!E1380) -> 1380 | G3: experiment | H3: =ROW(Cleaned_Transcripts!E1340) -> 1340 | I3: control | J3: =ROW(Cleaned_Transcripts!E1400) -> 1400 | K3: control | L3: =ROW(Cleaned_Transcripts!E1406) -> 1406 | M3: neutral | N3: =ROW(Cleaned_Transcripts!E1429) -> 1429 | O3: control | P3: =ROW(Cleaned_Transcripts!E1448) -> 1448 | Q3: control | R3: =ROW(Cleaned_Transcripts!E1343) -> 1343 | S3: control | T3: =ROW(Cleaned_Transcripts!E1517) -> 1517
A4: 3 | B4: =_xlfn.XLOOKUP(A4,participants!A:A,participants!C:C) -> experiment_first | C4: experiment | D4: =ROW(Cleaned_Transcripts!E1804) -> 1804 | E4: experiment | F4: =ROW(Cleaned_Transcripts!E1853) -> 1853 | G4: neutral | H4: =ROW(Cleaned_Transcripts!E1859) -> 1859 | I4: neutral | J4: =ROW(Cleaned_Transcripts!E1878) -> 1878 | K4: neutral | L4: -1 | M4: neutral | N4: -1 | O4: experiment | P4: =ROW(Cleaned_Transcripts!E1891) -> 1891 | Q4: control | R4: =ROW(Cleaned_Transcripts!E1929) -> 1929 | S4: experiment | T4: =ROW(Cleaned_Transcripts!E1968) -> 1968
A5: 4 | B5: =_xlfn.XLOOKUP(A5,participants!A:A,participants!C:C) -> control_first | C5: experiment | D5: =ROW(Cleaned_Transcripts!E2222) -> 2222 | E5: neutral | F5: =ROW(Cleaned_Transcripts!E2256) -> 2256 | G5: experiment | H5: =ROW(Cleaned_Transcripts!E2266) -> 2266 | I5: control | J5: =ROW(Cleaned_Transcripts!E2269) -> 2269 | K5: experiment | L5: =ROW(Cleaned_Transcripts!E2275) -> 2275 | M5: neutral | N5: =ROW(Cleaned_Transcripts!E2278) -> 2278 | O5: neutral | P5: -1 | Q5: experiment | R5: =ROW(Cleaned_Transcripts!E2306) -> 2306 | S5: neutral | T5: =ROW(Cleaned_Transcripts!E2347) -> 2347
A6: 5 | B6: =_xlfn.XLOOKUP(A6,participants!A:A,participants!C:C) -> experiment_first | C6: experiment | D6: =ROW(Cleaned_Transcripts!E2651) -> 2651 | E6: experiment | F6: =ROW(Cleaned_Transcripts!E2676) -> 2676 | G6: experiment | H6: =ROW(Cleaned_Transcripts!E2692) -> 2692 | I6: control | J6: =ROW(Cleaned_Transcripts!E2694) -> 2694 | K6: experiment | L6: =ROW(Cleaned_Transcripts!E2697) -> 2697 | M6: neutral | N6: =ROW(Cleaned_Transcripts!E2706) -> 2706 | O6: control | P6: =ROW(Cleaned_Transcripts!E2713) -> 2713 | Q6: experiment | R6: =ROW(Cleaned_Transcripts!E2719) -> 2719 | S6: experiment | T6: =ROW(Cleaned_Transcripts!E2760) -> 2760
A7: 6 | B7: =_xlfn.XLOOKUP(A7,participants!A:A,participants!C:C) -> control_first | C7: control | D7: =ROW(Cleaned_Transcripts!E3158) -> 3158 | E7: neutral | F7: =ROW(Cleaned_Transcripts!E3221) -> 3221 | G7: control | H7: =ROW(Cleaned_Transcripts!E3258) -> 3258 | I7: control | J7: =ROW(Cleaned_Transcripts!E3265) -> 3265 | K7: control | L7: =ROW(Cleaned_Transcripts!E3360) -> 3360 | M7: neutral | N7: -1 | O7: neutral | P7: =ROW(Cleaned_Transcripts!E3395) -> 3395 | Q7: neutral | R7: =ROW(Cleaned_Transcripts!E3398) -> 3398 | S7: control | T7: =ROW(Cleaned_Transcripts!E3507) -> 3507
A8: 7 | B8: =_xlfn.XLOOKUP(A8,participants!A:A,participants!C:C) -> experiment_first | C8: experiment | D8: =ROW(Cleaned_Transcripts!E4018) -> 4018 | E8: experiment | F8: =ROW(Cleaned_Transcripts!E4041) -> 4041 | G8: experiment | H8: =ROW(Cleaned_Transcripts!E4023) -> 4023 | I8: control | J8: =ROW(Cleaned_Transcripts!E4060) -> 4060 | K8: experiment | L8: =ROW(Cleaned_Transcripts!E4062) -> 4062 | M8: neutral | N8: =ROW(Cleaned_Transcripts!E4064) -> 4064 | O8: neutral | P8: =ROW(Cleaned_Transcripts!E4103) -> 4103 | Q8: control | R8: =ROW(Cleaned_Transcripts!E4117) -> 4117 | S8: control | T8: =ROW(Cleaned_Transcripts!E4183) -> 4183
A9: 8 | B9: =_xlfn.XLOOKUP(A9,participants!A:A,participants!C:C) -> experiment_first | C9: control | D9: =ROW(Cleaned_Transcripts!E4665) -> 4665 | E9: control | F9: =ROW(Cleaned_Transcripts!E4719) -> 4719 | G9: control | H9: =ROW(Cleaned_Transcripts!E4724) -> 4724 | I9: experiment | J9: =ROW(Cleaned_Transcripts!E4726) -> 4726 | K9: control | L9: =ROW(Cleaned_Transcripts!E4729) -> 4729 | M9: control | N9: =ROW(Cleaned_Transcripts!E4733) -> 4733 | O9: control | P9: =ROW(Cleaned_Transcripts!E4746) -> 4746 | Q9: control | R9: =ROW(Cleaned_Transcripts!E4749) -> 4749 | S9: control | T9: =ROW(Cleaned_Transcripts!E4789) -> 4789
A10: 9 | B10: =_xlfn.XLOOKUP(A10,participants!A:A,participants!C:C) -> control_first | C10: control | D10: =ROW(Cleaned_Transcripts!E5562) -> 5562 | E10: control | F10: =ROW(Cleaned_Transcripts!E5602) -> 5602 | G10: control | H10: =ROW(Cleaned_Transcripts!E5613) -> 5613 | I10: experiment | J10: =ROW(Cleaned_Transcripts!E5624) -> 5624 | K10: neutral | L10: =ROW(Cleaned_Transcripts!E5636) -> 5636 | M10: neutral | N10: =ROW(Cleaned_Transcripts!E5644) -> 5644 | O10: control | P10: =ROW(Cleaned_Transcripts!E5667) -> 5667 | Q10: control | R10: =ROW(Cleaned_Transcripts!E5677) -> 5677 | S10: experiment | T10: =ROW(Cleaned_Transcripts!E5709) -> 5709
A11: 10 | B11: =_xlfn.XLOOKUP(A11,participants!A:A,participants!C:C) -> control_first | C11: control | D11: =ROW(Cleaned_Transcripts!E5879) -> 5879 | E11: neutral | F11: =ROW(Cleaned_Transcripts!E5893) -> 5893 | G11: experiment | H11: =ROW(Cleaned_Transcripts!E5897) -> 5897 | I11: control | J11: =ROW(Cleaned_Transcripts!E5899) -> 5899 | K11: control | L11: =ROW(Cleaned_Transcripts!E5901) -> 5901 | M11: control | N11: =ROW(Cleaned_Transcripts!E5906) -> 5906 | O11: experiment | P11: =ROW(Cleaned_Transcripts!E5912) -> 5912 | Q11: neutral | R11: =ROW(Cleaned_Transcripts!E5917) -> 5917 | S11: experiment | T11: =ROW(Cleaned_Transcripts!E5940) -> 5940
A12: 11 | B12: =_xlfn.XLOOKUP(A12,participants!A:A,participants!C:C) -> experiment_first | C12: control | D12: =ROW(Cleaned_Transcripts!E6597) -> 6597 | E12: experiment | F12: =ROW(Cleaned_Transcripts!E6634) -> 6634 | G12: neutral | H12: =ROW(Cleaned_Transcripts!E6642) -> 6642 | I12: control | J12: =ROW(Cleaned_Transcripts!E6644) -> 6644 | K12: control | L12: =ROW(Cleaned_Transcripts!E6647) -> 6647 | M12: neutral | N12: =ROW(Cleaned_Transcripts!E6653) -> 6653 | O12: neutral | P12: =ROW(Cleaned_Transcripts!E6662) -> 6662 | Q12: experiment | R12: =ROW(Cleaned_Transcripts!E6605) -> 6605 | S12: control | T12: =ROW(Cleaned_Transcripts!E6690) -> 6690
A13: 12 | B13: =_xlfn.XLOOKUP(A13,participants!A:A,participants!C:C) -> control_first | C13: control | D13: =ROW(Cleaned_Transcripts!E7035) -> 7035 | E13: control | F13: =ROW(Cleaned_Transcripts!E7065) -> 7065 | G13: control | H13: =ROW(Cleaned_Transcripts!E7072) -> 7072 | I13: neutral | J13: -1 | K13: neutral | L13: -1 | M13: neutral | N13: =ROW(Cleaned_Transcripts!E7079) -> 7079 | O13: control | P13: =ROW(Cleaned_Transcripts!E7083) -> 7083 | Q13: experiment | R13: =ROW(Cleaned_Transcripts!E7091) -> 7091 | S13: control | T13: =ROW(Cleaned_Transcripts!E7117) -> 7117
A14: 13 | B14: =_xlfn.XLOOKUP(A14,participants!A:A,participants!C:C) -> control_first | C14: control | D14: =ROW(Cleaned_Transcripts!E7801) -> 7801 | E14: neutral | F14: =ROW(Cleaned_Transcripts!E7846) -> 7846 | G14: neutral | H14: =ROW(Cleaned_Transcripts!E7856) -> 7856 | I14: neutral | J14: =ROW(Cleaned_Transcripts!E7859) -> 7859 | K14: neutral | L14: =ROW(Cleaned_Transcripts!E7860) -> 7860 | M14: neutral | N14: =ROW(Cleaned_Transcripts!E7866) -> 7866 | O14: neutral | P14: =ROW(Cleaned_Transcripts!E7885) -> 7885 | Q14: neutral | R14: =ROW(Cleaned_Transcripts!E7894) -> 7894 | S14: neutral | T14: =ROW(Cleaned_Transcripts!E7951) -> 7951
A15: 14 | B15: =_xlfn.XLOOKUP(A15,participants!A:A,participants!C:C) -> experiment_first | C15: control | D15: =ROW(Cleaned_Transcripts!E8215) -> 8215 | E15: neutral | F15: =ROW(Cleaned_Transcripts!E8240) -> 8240 | G15: control | H15: =ROW(Cleaned_Transcripts!E8252) -> 8252 | I15: experiment | J15: =ROW(Cleaned_Transcripts!E8253) -> 8253 | K15: control | L15: =ROW(Cleaned_Transcripts!E8254) -> 8254 | M15: neutral | N15: =ROW(Cleaned_Transcripts!E8255) -> 8255 | O15: neutral | P15: =ROW(Cleaned_Transcripts!E8261) -> 8261 | Q15: neutral | R15: =ROW(Cleaned_Transcripts!E8265) -> 8265 | S15: experiment | T15: =ROW(Cleaned_Transcripts!E8302) -> 8302
A16: 15 | B16: =_xlfn.XLOOKUP(A16,participants!A:A,participants!C:C) -> experiment_first | C16: experiment | D16: =ROW(Cleaned_Transcripts!E8605) -> 8605 | E16: experiment | F16: =ROW(Cleaned_Transcripts!E8618) -> 8618 | G16: experiment | H16: =ROW(Cleaned_Transcripts!E8627) -> 8627 | I16: experiment | J16: =ROW(Cleaned_Transcripts!E8630) -> 8630 | K16: neutral | L16: =ROW(Cleaned_Transcripts!E8634) -> 8634 | M16: experiment | N16: =ROW(Cleaned_Transcripts!E8635) -> 8635 | O16: experiment | P16: =ROW(Cleaned_Transcripts!E8647) -> 8647 | Q16: neutral | R16: =ROW(Cleaned_Transcripts!E8651) -> 8651 | S16: experiment | T16: =ROW(Cleaned_Transcripts!E8693) -> 8693
A17: 16 | B17: =_xlfn.XLOOKUP(A17,participants!A:A,participants!C:C) -> experiment_first | C17: control | D17: =ROW(Cleaned_Transcripts!E9186) -> 9186 | E17: neutral | F17: =ROW(Cleaned_Transcripts!E9221) -> 9221 | G17: control | H17: =ROW(Cleaned_Transcripts!E9236) -> 9236 | I17: neutral | J17: =ROW(Cleaned_Transcripts!E9237) -> 9237 | K17: control | L17: =ROW(Cleaned_Transcripts!E9239) -> 9239 | M17: control | N17: =ROW(Cleaned_Transcripts!E9248) -> 9248 | O17: control | P17: =ROW(Cleaned_Transcripts!E9258) -> 9258 | Q17: neutral | R17: -1 | S17: control | T17: =ROW(Cleaned_Transcripts!E9323) -> 9323
A18: 17 | B18: =_xlfn.XLOOKUP(A18,participants!A:A,participants!C:C) -> control_first | C18: neutral | D18: =ROW(Cleaned_Transcripts!E9621) -> 9621 | E18: neutral | F18: =ROW(Cleaned_Transcripts!E9636) -> 9636 | G18: neutral | H18: -1 | I18: neutral | J18: =ROW(Cleaned_Transcripts!E9640) -> 9640 | K18: neutral | L18: =ROW(Cleaned_Transcripts!E9642) -> 9642 | M18: neutral | N18: =ROW(Cleaned_Transcripts!E9646) -> 9646 | O18: neutral | P18: =ROW(Cleaned_Transcripts!E9654) -> 9654 | Q18: neutral | R18: =ROW(Cleaned_Transcripts!E9656) -> 9656 | S18: neutral | T18: =ROW(Cleaned_Transcripts!E9694) -> 9694
A19: 18 | B19: =_xlfn.XLOOKUP(A19,participants!A:A,participants!C:C) -> control_first | C19: experiment | D19: =ROW(Cleaned_Transcripts!E10220) -> 10220 | E19: experiment | F19: =ROW(Cleaned_Transcripts!E10291) -> 10291 | G19: neutral | H19: -1 | I19: control | J19: =ROW(Cleaned_Transcripts!E10299) -> 10299 | K19: control | L19: =ROW(Cleaned_Transcripts!E10302) -> 10302 | M19: experiment | N19: =ROW(Cleaned_Transcripts!E10304) -> 10304 | O19: experiment | P19: =ROW(Cleaned_Transcripts!E10311) -> 10311 | Q19: experiment | R19: =ROW(Cleaned_Transcripts!E10313) -> 10313 | S19: experiment | T19: =ROW(Cleaned_Transcripts!E10348) -> 10348
A20: 19 | B20: =_xlfn.XLOOKUP(A20,participants!A:A,participants!C:C) -> experiment_first | C20: experiment | D20: =ROW(Cleaned_Transcripts!E11275) -> 11275 | E20: control | F20: =ROW(Cleaned_Transcripts!E11280) -> 11280 | G20: control | H20: =ROW(Cleaned_Transcripts!E11282) -> 11282 | I20: experiment | J20: =ROW(Cleaned_Transcripts!E11298) -> 11298 | K20: control | L20: =ROW(Cleaned_Transcripts!E11299) -> 11299 | M20: control | N20: =ROW(Cleaned_Transcripts!E11302) -> 11302 | O20: experiment | P20: =ROW(Cleaned_Transcripts!E11314) -> 11314 | Q20: neutral | R20: =ROW(Cleaned_Transcripts!E11318) -> 11318 | S20: experiment | T20: =ROW(Cleaned_Transcripts!E11348) -> 11348
A21: 20 | B21: =_xlfn.XLOOKUP(A21,participants!A:A,participants!C:C) -> control_first | C21: experiment | D21: =ROW(Cleaned_Transcripts!E11747) -> 11747 | E21: experiment | F21: =ROW(Cleaned_Transcripts!E11774) -> 11774 | G21: experiment | H21: =ROW(Cleaned_Transcripts!E11778) -> 11778 | I21: experiment | J21: =ROW(Cleaned_Transcripts!E11782) -> 11782 | K21: experiment | L21: =ROW(Cleaned_Transcripts!E11783) -> 11783 | M21: experiment | N21: =ROW(Cleaned_Transcripts!E11797) -> 11797 | O21: experiment | P21: =ROW(Cleaned_Transcripts!E11802) -> 11802 | Q21: experiment | R21: =ROW(Cleaned_Transcripts!E11804) -> 11804 | S21: experiment | T21: =ROW(Cleaned_Transcripts!E11856) -> 11856

Sheet Cleaned_Transcripts
A1: participant_id | B1: start | C1: end | D1: guess | E1: text | F1: speaker | G1: group | H1: variant | I1: source_type | J1: main_phase | K1: sub_phase | L1: deductive_code | M1: quotes | N1: inductive_codes
A2: 1 | B2: 1029 | C2: 9370 | E2: Ja, dann nochmal danke dir, dass du dir die Zeit genommen hast und die Nutzerstudie dauert | F2: Speaker 2 | G2: =_xlfn.XLOOKUP(A2,participants!A:A,participants!C:C) -> control_first | H2: =IF(J2 = "Chat 1", IF(P01__1[[#This Row],[group]] = "control_first", "control", "experiment"), IF(J2 = "Chat 2", IF(P01__1[[#This Row],[group]] = "control_first", "experiment", "control"), "")) | J2: General
A3: 1 | B3: 9370 | C3: 16450 | E3: so ungefähr 45 bis 60 Minuten, das Interview wird mit der Software OBS aufgezeichnet, um | F3: Speaker 2 | G3: =_xlfn.XLOOKUP(A3,participants!A:A,participants!C:C) -> control_first | H3: =IF(J3 = "Chat 1", IF(P01__1[[#This Row],[group]] = "control_first", "control", "experiment"), IF(J3 = "Chat 2", IF(P01__1[[#This Row],[group]] = "control_first", "experiment", "control"), "")) | J3: General
A4: 1 | B4: 16450 | C4: 22550 | E4: das dann später zu transkribieren und die Audio wird dann nach der Transkription gelöfft | F4: Speaker 2 | G4: =_xlfn.XLOOKUP(A4,participants!A:A,participants!C:C) -> control_first | H4: =IF(J4 = "Chat 1", IF(P01__1[[#This Row],[group]] = "control_first", "control", "experiment"), IF(J4 = "Chat 2", IF(P01__1[[#This Row],[group]] = "control_first", "experiment", "control"), "")) | J4: General
A5: 1 | B5: 22550 | C5: 28670 | E5: und du kannst auch während des Interviews immer stoppen und deine Einwilligungen zurückziehen | F5: Speaker 2 | G5: =_xlfn.XLOOKUP(A5,participants!A:A,participants!C:C) -> control_first | H5: =IF(J5 = "Chat 1", IF(P01__1[[#This Row],[group]] = "control_first", "control", "experiment"), IF(J5 = "Chat 2", IF(P01__1[[#This Row],[group]] = "control_first", "experiment", "control"), "")) | J5: General
A6: 1 | B6: 28670 | C6: 35210 | E6: ohne irgendwelche Gründe zu benennen oder negative Folgen davon zu bekommen und deswegen | F6: Speaker 2 | G6: =_xlfn.XLOOKUP(A6,participants!A:A,participants!C:C) -> control_first | H6: =IF(J6 = "Chat 1", IF(P01__1[[#This Row],[group]] = "control_first", "control", "experiment"), IF(J6 = "Chat 2", IF(P01__1[[#This Row],[group]] = "control_first", "experiment", "control"), "")) | J6: General
A7: 1 | B7: 35210 | C7: 38090 | E7: einmal die Frage, ob du damit einverstanden bist, dass ich das aufzeichne? | F7: Speaker 2 | G7: =_xlfn.XLOOKUP(A7,participants!A:A,participants!C:C) -> control_first | H7: =IF(J7 = "Chat 1", IF(P01__1[[#This Row],[group]] = "control_first", "control", "experiment"), IF(J7 = "Chat 2", IF(P01__1[[#This Row],[group]] = "control_first", "experiment", "control"), "")) | J7: General
A8: 1 | B8: 39390 | C8: 39550 | E8: Ja. | F8: Speaker 2 | G8: =_xlfn.XLOOKUP(A8,participants!A:A,participants!C:C) -> control_first | H8: =IF(J8 = "Chat 1", IF(P01__1[[#This Row],[group]] = "control_first", "control", "experiment"), IF(J8 = "Chat 2", IF(P01__1[[#This Row],[group]] = "control_first", "experiment", "control"), "")) | J8: General
A9: 1 | B9: 40250 | C9: 41070 | E9: Okay, perfekt. | F9: Speaker 2 | G9: =_xlfn.XLOOKUP(A9,participants!A:A,participants!C:C) -> control_first | H9: =IF(J9 = "Chat 1", IF(P01__1[[#This Row],[group]] = "control_first", "control", "experiment"), IF(J9 = "Chat 2", IF(P01__1[[#This Row],[group]] = "control_first", "experiment", "control"), "")) | J9: General
A10: 1 | B10: 42690 | C10: 50650 | E10: Und genau, dann einmal zur Struktur, also du hast ja schon den Link bekommen zu der App | F10: Speaker 2 | G10: =_xlfn.XLOOKUP(A10,participants!A:A,participants!C:C) -> control_first | H10: =IF(J10 = "Chat 1", IF(P01__1[[#This Row],[group]] = "control_first", "control", "experiment"), IF(J10 = "Chat 2", IF(P01__1[[#This Row],[group]] = "control_first", "experiment", "control"), "")) | J10: General
A11: 1 | B11: 51530 | C11: 57910 | E11: und das sieht wie folgendermaßen aus, die Nutzerstudie, zuerst musst du ein kleines Onboarding | F11: Speaker 2 | G11: =_xlfn.XLOOKUP(A11,participants!A:A,participants!C:C) -> control_first | H11: =IF(J11 = "Chat 1", IF(P01__1[[#This Row],[group]] = "control_first", "control", "experiment"), IF(J11 = "Chat 2", IF(P01__1[[#This Row],[group]] = "control_first", "experiment", "control"), "")) | J11: General
A12: 1 | B12: 57910 | C12: 65030 | E12: machen, um ein paar Fragen zu beantworten, dann hast du eine Konversation als Warm-up | F12: Speaker 2 | G12: =_xlfn.XLOOKUP(A12,participants!A:A,participants!C:C) -> control_first | H12: =IF(J12 = "Chat 1", IF(P01__1[[#This Row],[group]] = "control_first", "control", "experiment"), IF(J12 = "Chat 2", IF(P01__1[[#This Row],[group]] = "control_first", "experiment", "control"), "")) | J12: General
A13: 1 | B13: 65030 | C13: 70770 | E13: und dann zwei weitere Konversationen und nach jeder Konversation hast du nochmal so eine | F13: Speaker 2 | G13: =_xlfn.XLOOKUP(A13,participants!A:A,participants!C:C) -> control_first | H13: =IF(J13 = "Chat 1", IF(P01__1[[#This Row],[group]] = "control_first", "control", "experiment"), IF(J13 = "Chat 2", IF(P01__1[[#This Row],[group]] = "control_first", "experiment", "control"), "")) | J13: General
... A28: 1 | B28: 244530 | C28: 244870 | E28: Okay. | F28: Speaker 1 | G28: =_xlfn.XLOOKUP(A28,participants!A:A,participants!C:C) -> control_first | H28: =IF(J28 = "Chat 1", IF(P01__1[[#This Row],[group]] = "control_first", "control", "experiment"), IF(J28 = "Chat 2", IF(P01__1[[#This Row],[group]] = "control_first", "experiment", "control"), "")) | J28: General
A29: 1 | B29: 247190 | C29: 252470 | E29: Ja, ich glaube, die Language-Level hier sind relativ übersichtlich, da bin ich auf jeden Fall hier. | F29: Speaker 1 | G29: =_xlfn.XLOOKUP(A29,participants!A:A,participants!C:C) -> control_first | H29: =IF(J29 = "Chat 1", IF(P01__1[[#This Row],[group]] = "control_first", "control", "experiment"), IF(J29 = "Chat 2", IF(P01__1[[#This Row],[group]] = "control_first", "experiment", "control"), "")) | J29: Onboarding | L29: GEN_UI_UX
A30: 1 | B30: 255730 | C30: 258329 | E30: Ich schreibe so ein bisschen mit, wenn nicht, dass du dich wunderst. | F30: Speaker 2 | G30: =_xlfn.XLOOKUP(A30,participants!A:A,participants!C:C) -> control_first | H30: =IF(J30 = "Chat 1", IF(P01__1[[#This Row],[group]] = "control_first", "control", "experiment"), IF(J30 = "Chat 2", IF(P01__1[[#This Row],[group]] = "control_first", "experiment", "control"), "")) | J30: Onboarding
A31: 1 | B31: 259630 | C31: 263250 | E31: Ja, meine Muttersprache ist Deutsch. | F31: Speaker 1 | G31: =_xlfn.XLOOKUP(A31,participants!A:A,participants!C:C) -> control_first | H31: =IF(J31 = "Chat 1", IF(P01__1[[#This Row],[group]] = "control_first", "control", "experiment"), IF(J31 = "Chat 2", IF(P01__1[[#This Row],[group]] = "control_first", "experiment", "control"), "")) | J31: Onboarding
A32: 1 | B32: 263250 | C32: 266610 | E32: Ah, ich kann nur eine auswählen, okay. | F32: Speaker 1 | G32: =_xlfn.XLOOKUP(A32,participants!A:A,participants!C:C) -> control_first | H32: =IF(J32 = "Chat 1", IF(P01__1[[#This Row],[group]] = "control_first", "control", "experiment"), IF(J32 = "Chat 2", IF(P01__1[[#This Row],[group]] = "control_first", "experiment", "control"), "")) | J32: Onboarding
A33: 1 | B33: 268730 | C33: 271330 | E33: Aber ist bei mir auch richtig mit einer Muttersprache? | F33: Speaker 1 | G33: =_xlfn.XLOOKUP(A33,participants!A:A,participants!C:C) -> control_first | H33: =IF(J33 = "Chat 1", IF(P01__1[[#This Row],[group]] = "control_first", "control", "experiment"), IF(J33 = "Chat 2", IF(P01__1[[#This Row],[group]] = "control_first", "experiment", "control"), "")) | J33: Onboarding
A34: 1 | B34: 279480 | C34: 286180 | E34: Do you struggle with up to five? | F34: Speaker 1 | G34: =_xlfn.XLOOKUP(A34,participants!A:A,participants!C:C) -> control_first | H34: =IF(J34 = "Chat 1", IF(P01__1[[#This Row],[group]] = "control_first", "control", "experiment"), IF(J34 = "Chat 2", IF(P01__1[[#This Row],[group]] = "control_first", "experiment", "control"), "")) | J34: Onboarding
A35: 1 | B35: 286360 | C35: 286560 | E35: Okay. | F35: Speaker 1 | G35: =_xlfn.XLOOKUP(A35,participants!A:A,participants!C:C) -> control_first | H35: =IF(J35 = "Chat 1", IF(P01__1[[#This Row],[group]] = "control_first", "control", "experiment"), IF(J35 = "Chat 2", IF(P01__1[[#This Row],[group]] = "control_first", "experiment", "control"), "")) | J35: Onboarding
A36: 1 | B36: 289830 | C36: 295250 | E36: Boah, ja, die Gendern im Spanischen kann ich mir nicht so merken. | F36: Speaker 1 | G36: =_xlfn.XLOOKUP(A36,participants!A:A,participants!C:C) -> control_first | H36: =IF(J36 = "Chat 1", IF(P01__1[[#This Row],[group]] = "control_first", "control", "experiment"), IF(J36 = "Chat 2", IF(P01__1[[#This Row],[group]] = "control_first", "experiment", "control"), "")) | J36: Onboarding
A37: 1 | B37: 296710 | C37: 298050 | E37: Mathikregeln auch noch schwierig. | F37: Speaker 1 | G37: =_xlfn.XLOOKUP(A37,participants!A:A,participants!C:C) -> control_first | H37: =IF(J37 = "Chat 1", IF(P01__1[[#This Row],[group]] = "control_first", "control", "experiment"), IF(J37 = "Chat 2", IF(P01__1[[#This Row],[group]] = "control_first", "experiment", "control"), "")) | J37: Onboarding
A38: 1 | B38: 300770 | C38: 314520 | E38: Die Frage ist, gehe ich jetzt eher auf die Sachen, die halt so ganz schwer sind, oder so Sachen, mit denen ich auch noch struggle. | F38: Speaker 1 | G38: =_xlfn.XLOOKUP(A38,participants!A:A,participants!C:C) -> control_first | H38: =IF(J38 = "Chat 1", IF(P01__1[[#This Row],[group]] = "control_first", "control", "experiment"), IF(J38 = "Chat 2", IF(P01__1[[#This Row],[group]] = "control_first", "experiment", "control"), "")) | J38: Onboarding
A39: 1 | B39: 315240 | C39: 317980 | E39: Eigentlich bin ich gerade eher, glaube ich, mir am vieren abwählen. | F39: Speaker 1 | G39: =_xlfn.XLOOKUP(A39,participants!A:A,participants!C:C) -> control_first | H39: =IF(J39 = "Chat 1", IF(P01__1[[#This Row],[group]] = "control_first", "control", "experiment"), IF(J39 = "Chat 2", IF(P01__1[[#This Row],[group]] = "control_first", "experiment", "control"), "")) | J39: Onboarding
A40: 1 | B40: 321980 | C40: 324620 | E40: Ja, four-leaf-speaking ist reine Kopfsache. | F40: Speaker 1 | G40: =_xlfn.XLOOKUP(A40,participants!A:A,participants!C:C) -> control_first | H40: =IF(J40 = "Chat 1", IF(P01__1[[#This Row],[group]] = "control_first", "control", "experiment"), IF(J40 = "Chat 2", IF(P01__1[[#This Row],[group]] = "control_first", "experiment", "control"), "")) | J40: Onboarding
A41: 1 | B41: 325660 | C41: 327440 | E41: Ja, konjugieren ist immer ein bisschen schwierig. | F41: Speaker 1 | G41: =_xlfn.XLOOKUP(A41,participants!A:A,participants!C:C) -> control_first | H41: =IF(J41 = "Chat 1", IF(P01__1[[#This Row],[group]] = "control_first", "control", "experiment"), IF(J41 = "Chat 2", IF(P01__1[[#This Row],[group]] = "control_first", "experiment", "control"), "")) | J41: Onboarding
... A66: 1 | B66: 531250 | C66: 533550 | E66: Das sollte vielleicht nicht mal beim selben rauskommen. | F66: Speaker 1 | G66: =_xlfn.XLOOKUP(A66,participants!A:A,participants!C:C) -> control_first | H66: =IF(J66 = "Chat 1", IF(P01__1[[#This Row],[group]] = "control_first", "control", "experiment"), IF(J66 = "Chat 2", IF(P01__1[[#This Row],[group]] = "control_first", "experiment", "control"), "")) | J66: Onboarding
A67: 1 | B67: 539500 | C67: 541360 | E67: Sieht lustig aus. | F67: Speaker 2 | G67: =_xlfn.XLOOKUP(A67,participants!A:A,participants!C:C) -> control_first | H67: =IF(J67 = "Chat 1", IF(P01__1[[#This Row],[group]] = "control_first", "control", "experiment"), IF(J67 = "Chat 2", IF(P01__1[[#This Row],[group]] = "control_first", "experiment", "control"), "")) | J67: Onboarding | L67: CUST_Partner
A68: 1 | B68: 542060 | C68: 544460 | E68: Du musst nach oben den Namen eingeben. | F68: Speaker 2 | G68: =_xlfn.XLOOKUP(A68,participants!A:A,participants!C:C) -> control_first | H68: =IF(J68 = "Chat 1", IF(P01__1[[#This Row],[group]] = "control_first", "control", "experiment"), IF(J68 = "Chat 2", IF(P01__1[[#This Row],[group]] = "control_first", "experiment", "control"), "")) | J68: Onboarding
A69: 1 | B69: 545200 | C69: 546640 | E69: Oh, ich muss den Namen eingeben, ja. | F69: Speaker 2 | G69: =_xlfn.XLOOKUP(A69,participants!A:A,participants!C:C) -> control_first | H69: =IF(J69 = "Chat 1", IF(P01__1[[#This Row],[group]] = "control_first", "control", "experiment"), IF(J69 = "Chat 2", IF(P01__1[[#This Row],[group]] = "control_first", "experiment", "control"), "")) | J69: Onboarding
A70: 1 | B70: 548860 | C70: 551640 | E70: Stimmt, wer nicht blind ist. | F70: Speaker 1 | G70: =_xlfn.XLOOKUP(A70,participants!A:A,participants!C:C) -> control_first | H70: =IF(J70 = "Chat 1", IF(P01__1[[#This Row],[group]] = "control_first", "control", "experiment"), IF(J70 = "Chat 2", IF(P01__1[[#This Row],[group]] = "control_first", "experiment", "control"), "")) | J70: Onboarding
A71: 1 | B71: 556650 | C71: 561750 | E71: Wenn ich mich jetzt schon einmal Frucht benannt habe, dann kriegt ihr jetzt auch einen Fruchtnamen. | F71: Speaker 1 | G71: =_xlfn.XLOOKUP(A71,participants!A:A,participants!C:C) -> control_first | H71: =IF(J71 = "Chat 1", IF(P01__1[[#This Row],[group]] = "control_first", "control", "experiment"), IF(J71 = "Chat 2", IF(P01__1[[#This Row],[group]] = "control_first", "experiment", "control"), "")) | J71: Onboarding
A72: 1 | B72: 564330 | C72: 567390 | E72: Okay, also ich vermute, das ist jetzt das erste Szenario. | F72: Speaker 1 | G72: =_xlfn.XLOOKUP(A72,participants!A:A,participants!C:C) -> control_first | H72: =IF(J72 = "Chat 1", IF(P01__1[[#This Row],[group]] = "control_first", "control", "experiment"), IF(J72 = "Chat 2", IF(P01__1[[#This Row],[group]] = "control_first", "experiment", "control"), "")) | J72: Onboarding
A73: 1 | B73: 572250 | C73: 574250 | E73: Okay, dann Generate Task. | F73: Speaker 1 | G73: =_xlfn.XLOOKUP(A73,participants!A:A,participants!C:C) -> control_first | H73: =IF(J73 = "Chat 1", IF(P01__1[[#This Row],[group]] = "control_first", "control", "experiment"), IF(J73 = "Chat 2", IF(P01__1[[#This Row],[group]] = "control_first", "experiment", "control"), "")) | J73: Onboarding
A74: 1 | B74: 574490 | C74: 576250 | E74: Klingt so, als müsste ich jetzt ein paar Aufgaben. | F74: Speaker 2 | G74: =_xlfn.XLOOKUP(A74,participants!A:A,participants!C:C) -> control_first | H74: =IF(J74 = "Chat 1", IF(P01__1[[#This Row],[group]] = "control_first", "control", "experiment"), IF(J74 = "Chat 2", IF(P01__1[[#This Row],[group]] = "control_first", "experiment", "control"), "")) | J74: Onboarding
A75: 1 | B75: 576250 | C75: 578530 | E75: Genau, bevor du weitergehst. | F75: Speaker 2 | G75: =_xlfn.XLOOKUP(A75,participants!A:A,participants!C:C) -> control_first | H75: =IF(J75 = "Chat 1", IF(P01__1[[#This Row],[group]] = "control_first", "control", "experiment"), IF(J75 = "Chat 2", IF(P01__1[[#This Row],[group]] = "control_first", "experiment", "control"), "")) | J75: Onboarding
A76: 1 | B76: 579030 | C76: 584190 | E76: Auch wichtig, jedes Szenario oder jeder Chat hat ein Limit. | F76: Speaker 2 | G76: =_xlfn.XLOOKUP(A76,participants!A:A,participants!C:C) -> control_first | H76: =IF(J76 = "Chat 1", IF(P01__1[[#This Row],[group]] = "control_first", "control", "experiment"), IF(J76 = "Chat 2", IF(P01__1[[#This Row],[group]] = "control_first", "experiment", "control"), "")) | J76: Onboarding
A77: 1 | B77: 584450 | C77: 587210 | E77: Also man kann maximal 15 Nachrichten schreiben. | F77: Speaker 2 | G77: =_xlfn.XLOOKUP(A77,participants!A:A,participants!C:C) -> control_first | H77: =IF(J77 = "Chat 1", IF(P01__1[[#This Row],[group]] = "control_first", "control", "experiment"), IF(J77 = "Chat 2", IF(P01__1[[#This Row],[group]] = "control_first", "experiment", "control"), "")) | J77: Onboarding
A78: 1 | B78: 588790 | C78: 591410 | E78: Also 15 Nachrichten jeder. | F78: Speaker 2 | G78: =_xlfn.XLOOKUP(A78,participants!A:A,participants!C:C) -> control_first | H78: =IF(J78 = "Chat 1", IF(P01__1[[#This Row],[group]] = "control_first", "control", "experiment"), IF(J78 = "Chat 2", IF(P01__1[[#This Row],[group]] = "control_first", "experiment", "control"), "")) | J78: Onboarding
A79: 1 | B79: 593470 | C79: 603210 | E79: Aber das Limit ist trotzdem hochgesetzt, damit auch angeregt wird, dass man eine Konversation hat und nicht nur versucht, die Aufgaben zu lösen. | F79: Speaker 2 | G79: =_xlfn.XLOOKUP(A79,participants!A:A,participants!C:C) -> control_first | H79: =IF(J79 = "Chat 1", IF(P01__1[[#This Row],[group]] = "control_first", "control", "experiment"), IF(J79 = "Chat 2", IF(P01__1[[#This Row],[group]] = "control_first", "experiment", "control"), "")) | J79: Onboarding
... A114: 1 | B114: 743700 | C114: 744020 | E114: Ähm. | F114: Speaker 1 | G114: =_xlfn.XLOOKUP(A114,participants!A:A,participants!C:C) -> control_first | H114: =IF(J114 = "Chat 1", IF(P01__1[[#This Row],[group]] = "control_first", "control", "experiment"), IF(J114 = "Chat 2", IF(P01__1[[#This Row],[group]] = "control_first", "experiment", "control"), "")) | J114: Warmup
A115: 1 | B115: 746730 | C115: 748990 | E115: Schon mal sehr angenehm, diesen Sprachknopf zu haben. | F115: Speaker 1 | G115: =_xlfn.XLOOKUP(A115,participants!A:A,participants!C:C) -> control_first | H115: =IF(J115 = "Chat 1", IF(P01__1[[#This Row],[group]] = "control_first", "control", "experiment"), IF(J115 = "Chat 2", IF(P01__1[[#This Row],[group]] = "control_first", "experiment", "control"), "")) | J115: Warmup | L115: GEN_UI_UX
A116: 1 | B116: 749090 | C116: 754130 | E116: Da muss man sicherlich die ganze Zeit ruhig sein, bis man irgendwie eine Idee hat. | F116: Speaker 1 | G116: =_xlfn.XLOOKUP(A116,participants!A:A,participants!C:C) -> control_first | H116: =IF(J116 = "Chat 1", IF(P01__1[[#This Row],[group]] = "control_first", "control", "experiment"), IF(J116 = "Chat 2", IF(P01__1[[#This Row],[group]] = "control_first", "experiment", "control"), "")) | J116: Warmup
A117: 1 | B117: 755230 | C117: 757210 | E117: Okay, ich glaube, ich verstehe einigermaßen. | F117: Speaker 1 | G117: =_xlfn.XLOOKUP(A117,participants!A:A,participants!C:C) -> control_first | H117: =IF(J117 = "Chat 1", IF(P01__1[[#This Row],[group]] = "control_first", "control", "experiment"), IF(J117 = "Chat 2", IF(P01__1[[#This Row],[group]] = "control_first", "experiment", "control"), "")) | J117: Warmup
A118: 1 | B118: 757310 | C118: 758770 | E118: Das ist ja, glaube ich, nicht ganz alles. | F118: Speaker 1 | G118: =_xlfn.XLOOKUP(A118,participants!A:A,participants!C:C) -> control_first | H118: =IF(J118 = "Chat 1", IF(P01__1[[#This Row],[group]] = "control_first", "control", "experiment"), IF(J118 = "Chat 2", IF(P01__1[[#This Row],[group]] = "control_first", "experiment", "control"), "")) | J118: Warmup
A119: 1 | B119: 759690 | C119: 761770 | E119: Hola, me llamo Orange. | F119: Speaker 1 | G119: =_xlfn.XLOOKUP(A119,participants!A:A,participants!C:C) -> control_first | H119: =IF(J119 = "Chat 1", IF(P01__1[[#This Row],[group]] = "control_first", "control", "experiment"), IF(J119 = "Chat 2", IF(P01__1[[#This Row],[group]] = "control_first", "experiment", "control"), "")) | J119: Warmup
A120: 1 | B120: 762990 | C120: 767600 | E120: Es ist auch trocken. | F120: Speaker 1 | G120: =_xlfn.XLOOKUP(A120,participants!A:A,participants!C:C) -> control_first | H120: =IF(J120 = "Chat 1", IF(P01__1[[#This Row],[group]] = "control_first", "control", "experiment"), IF(J120 = "Chat 2", IF(P01__1[[#This Row],[group]] = "control_first", "experiment", "control"), "")) | J120: Warmup
A121: 1 | B121: 770370 | C121: 771590 | E121: Te sientes? | F121: Speaker 1 | G121: =_xlfn.XLOOKUP(A121,participants!A:A,participants!C:C) -> control_first | H121: =IF(J121 = "Chat 1", IF(P01__1[[#This Row],[group]] = "control_first", "control", "experiment"), IF(J121 = "Chat 2", IF(P01__1[[#This Row],[group]] = "control_first", "experiment", "control"), "")) | J121: Warmup
A122: 1 | B122: 773190 | C122: 773290 | E122: Ähm. | F122: Speaker 1 | G122: =_xlfn.XLOOKUP(A122,participants!A:A,participants!C:C) -> control_first | H122: =IF(J122 = "Chat 1", IF(P01__1[[#This Row],[group]] = "control_first", "control", "experiment"), IF(J122 = "Chat 2", IF(P01__1[[#This Row],[group]] = "control_first", "experiment", "control"), "")) | J122: Warmup
A123: 1 | B123: 774070 | C123: 774370 | E123: Hm. | F123: Speaker 1 | G123: =_xlfn.XLOOKUP(A123,participants!A:A,participants!C:C) -> control_first | H123: =IF(J123 = "Chat 1", IF(P01__1[[#This Row],[group]] = "control_first", "control", "experiment"), IF(J123 = "Chat 2", IF(P01__1[[#This Row],[group]] = "control_first", "experiment", "control"), "")) | J123: Warmup
A124: 1 | B124: 777400 | C124: 778840 | E124: Jetzt stecke ich ein bisschen fest. | F124: Speaker 1 | G124: =_xlfn.XLOOKUP(A124,participants!A:A,participants!C:C) -> control_first | H124: =IF(J124 = "Chat 1", IF(P01__1[[#This Row],[group]] = "control_first", "control", "experiment"), IF(J124 = "Chat 2", IF(P01__1[[#This Row],[group]] = "control_first", "experiment", "control"), "")) | J124: Warmup
A125: 1 | B125: 779300 | C125: 779840 | E125: Was macht das? | F125: Speaker 1 | G125: =_xlfn.XLOOKUP(A125,participants!A:A,participants!C:C) -> control_first | H125: =IF(J125 = "Chat 1", IF(P01__1[[#This Row],[group]] = "control_first", "control", "experiment"), IF(J125 = "Chat 2", IF(P01__1[[#This Row],[group]] = "control_first", "experiment", "control"), "")) | J125: Warmup
A126: 1 | B126: 780000 | C126: 781220 | E126: Ah, da könnte ich es tippen. | F126: Speaker 1 | G126: =_xlfn.XLOOKUP(A126,participants!A:A,participants!C:C) -> control_first | H126: =IF(J126 = "Chat 1", IF(P01__1[[#This Row],[group]] = "control_first", "control", "experiment"), IF(J126 = "Chat 2", IF(P01__1[[#This Row],[group]] = "control_first", "experiment", "control"), "")) | J126: Warmup
A127: 1 | B127: 785190 | C127: 786810 | E127: Our personalization. | F127: Speaker 1 | G127: =_xlfn.XLOOKUP(A127,participants!A:A,participants!C:C) -> control_first | H127: =IF(J127 = "Chat 1", IF(P01__1[[#This Row],[group]] = "control_first", "control", "experiment"), IF(J127 = "Chat 2", IF(P01__1[[#This Row],[group]] = "control_first", "experiment", "control"), "")) | J127: Warmup
... A180: 1 | B180: 1006260 | C180: 1008740 | E180: Verstehe ich meistens dann einen Satz oder so wie. | F180: Speaker 1 | G180: =_xlfn.XLOOKUP(A180,participants!A:A,participants!C:C) -> control_first | H180: =IF(J180 = "Chat 1", IF(P01__1[[#This Row],[group]] = "control_first", "control", "experiment"), IF(J180 = "Chat 2", IF(P01__1[[#This Row],[group]] = "control_first", "experiment", "control"), "")) | J180: Warmup
A181: 1 | B181: 1008900 | C181: 1011660 | E181: Aber ich traue mich nicht so ganz, die KI zu fragen. Ob sie nochmal den zweiten oder dritten erklären kann. Deswegen frage ich einfach, ob sie alles erklärt. Wie meinst du das genau? Ich hab manchmal irgendwie den Eindruck. Weil so. KI. Wenn man dann. Mit denen redet. Dass sie. Wenn man dann so sagt. Erklär mal den zweiten Satz. Dass sie sich dann vorzählen. Und den dritten erklären. Oder irgendwie so. | F181: Speaker 1 | G181: =_xlfn.XLOOKUP(A181,participants!A:A,participants!C:C) -> control_first | H181: =IF(J181 = "Chat 1", IF(P01__1[[#This Row],[group]] = "control_first", "control", "experiment"), IF(J181 = "Chat 2", IF(P01__1[[#This Row],[group]] = "control_first", "experiment", "control"), "")) | J181: Warmup | M181: QUOTE
A182: 1 | B182: 1036609 | C182: 1036790 | E182: Hm. | F182: Speaker 2 | G182: =_xlfn.XLOOKUP(A182,participants!A:A,participants!C:C) -> control_first | H182: =IF(J182 = "Chat 1", IF(P01__1[[#This Row],[group]] = "control_first", "control", "experiment"), IF(J182 = "Chat 2", IF(P01__1[[#This Row],[group]] = "control_first", "experiment", "control"), "")) | J182: Warmup
A183: 1 | B183: 1037470 | C183: 1037869 | E183: Ähm. | F183: Speaker 1 | G183: =_xlfn.XLOOKUP(A183,participants!A:A,participants!C:C) -> control_first | H183: =IF(J183 = "Chat 1", IF(P01__1[[#This Row],[group]] = "control_first", "control", "experiment"), IF(J183 = "Chat 2", IF(P01__1[[#This Row],[group]] = "control_first", "experiment", "control"), "")) | J183: Warmup
A184: 1 | B184: 1042240 | C184: 1042599 | E184: Okay. | F184: Speaker 1 | G184: =_xlfn.XLOOKUP(A184,participants!A:A,participants!C:C) -> control_first | H184: =IF(J184 = "Chat 1", IF(P01__1[[#This Row],[group]] = "control_first", "control", "experiment"), IF(J184 = "Chat 2", IF(P01__1[[#This Row],[group]] = "control_first", "experiment", "control"), "")) | J184: Warmup
A185: 1 | B185: 1043160 | C185: 1046000 | E185: Die Formatierung kapiere ich jetzt nicht ganz. | F185: Speaker 1 | G185: =_xlfn.XLOOKUP(A185,participants!A:A,participants!C:C) -> control_first | H185: =IF(J185 = "Chat 1", IF(P01__1[[#This Row],[group]] = "control_first", "control", "experiment"), IF(J185 = "Chat 2", IF(P01__1[[#This Row],[group]] = "control_first", "experiment", "control"), "")) | J185: Warmup
A186: 1 | B186: 1047060 | C186: 1047339 | E186: Ah. | F186: Speaker 1 | G186: =_xlfn.XLOOKUP(A186,participants!A:A,participants!C:C) -> control_first | H186: =IF(J186 = "Chat 1", IF(P01__1[[#This Row],[group]] = "control_first", "control", "experiment"), IF(J186 = "Chat 2", IF(P01__1[[#This Row],[group]] = "control_first", "experiment", "control"), "")) | J186: Warmup
A187: 1 | B187: 1047440 | C187: 1049980 | E187: Das erklärt mir hier, wie es formatiert ist. | F187: Speaker 1 | G187: =_xlfn.XLOOKUP(A187,participants!A:A,participants!C:C) -> control_first | H187: =IF(J187 = "Chat 1", IF(P01__1[[#This Row],[group]] = "control_first", "control", "experiment"), IF(J187 = "Chat 2", IF(P01__1[[#This Row],[group]] = "control_first", "experiment", "control"), "")) | J187: Warmup
A188: 1 | B188: 1051820 | C188: 1053000 | E188: Spanish, English, Note. | F188: Speaker 1 | G188: =_xlfn.XLOOKUP(A188,participants!A:A,participants!C:C) -> control_first | H188: =IF(J188 = "Chat 1", IF(P01__1[[#This Row],[group]] = "control_first", "control", "experiment"), IF(J188 = "Chat 2", IF(P01__1[[#This Row],[group]] = "control_first", "experiment", "control"), "")) | J188: Warmup
A189: 1 | B189: 1053140 | C189: 1053240 | E189: Oder? | F189: Speaker 1 | G189: =_xlfn.XLOOKUP(A189,participants!A:A,participants!C:C) -> control_first | H189: =IF(J189 = "Chat 1", IF(P01__1[[#This Row],[group]] = "control_first", "control", "experiment"), IF(J189 = "Chat 2", IF(P01__1[[#This Row],[group]] = "control_first", "experiment", "control"), "")) | J189: Warmup
A190: 1 | B190: 1054720 | C190: 1055120 | E190: Genau. | F190: Speaker 2 | G190: =_xlfn.XLOOKUP(A190,participants!A:A,participants!C:C) -> control_first | H190: =IF(J190 = "Chat 1", IF(P01__1[[#This Row],[group]] = "control_first", "control", "experiment"), IF(J190 = "Chat 2", IF(P01__1[[#This Row],[group]] = "control_first", "experiment", "control"), "")) | J190: Warmup
A191: 1 | B191: 1055340 | C191: 1056420 | E191: Ich glaube. | F191: Speaker 1 | G191: =_xlfn.XLOOKUP(A191,participants!A:A,participants!C:C) -> control_first | H191: =IF(J191 = "Chat 1", IF(P01__1[[#This Row],[group]] = "control_first", "control", "experiment"), IF(J191 = "Chat 2", IF(P01__1[[#This Row],[group]] = "control_first", "experiment", "control"), "")) | J191: Warmup
A192: 1 | B192: 1056880 | C192: 1057180 | E192: Spanish, English, Note. | F192: Speaker 2 | G192: =_xlfn.XLOOKUP(A192,participants!A:A,participants!C:C) -> control_first | H192: =IF(J192 = "Chat 1", IF(P01__1[[#This Row],[group]] = "control_first", "control", "experiment"), IF(J192 = "Chat 2", IF(P01__1[[#This Row],[group]] = "control_first", "experiment", "control"), "")) | J192: Warmup
A193: 1 | B193: 1057180 | C193: 1057860 | E193: Ah. | F193: Speaker 2 | G193: =_xlfn.XLOOKUP(A193,participants!A:A,participants!C:C) -> control_first | H193: =IF(J193 = "Chat 1", IF(P01__1[[#This Row],[group]] = "control_first", "control", "experiment"), IF(J193 = "Chat 2", IF(P01__1[[#This Row],[group]] = "control_first", "experiment", "control"), "")) | J193: Warmup
... A221: 1 | B221: 1117850 | C221: 1119230 | E221: Dann kopiere ich die doch einfach. Ich schreibe mal noch bitte mit rein. Dann wird die Antwort vielleicht besser. | F221: Speaker 1 | G221: =_xlfn.XLOOKUP(A221,participants!A:A,participants!C:C) -> control_first | H221: =IF(J221 = "Chat 1", IF(P01__1[[#This Row],[group]] = "control_first", "control", "experiment"), IF(J221 = "Chat 2", IF(P01__1[[#This Row],[group]] = "control_first", "experiment", "control"), "")) | J221: Warmup
A222: 1 | B222: 1173790 | C222: 1175110 | E222: Das mit dem Tutor ist schon gut. | F222: Speaker 1 | G222: =_xlfn.XLOOKUP(A222,participants!A:A,participants!C:C) -> control_first | H222: =IF(J222 = "Chat 1", IF(P01__1[[#This Row],[group]] = "control_first", "control", "experiment"), IF(J222 = "Chat 2", IF(P01__1[[#This Row],[group]] = "control_first", "experiment", "control"), "")) | J222: Warmup | L222: UX_Efficiency | M222: QUOTE
A223: 1 | B223: 1175850 | C223: 1176070 | E223: Ah. | F223: Speaker 1 | G223: =_xlfn.XLOOKUP(A223,participants!A:A,participants!C:C) -> control_first | H223: =IF(J223 = "Chat 1", IF(P01__1[[#This Row],[group]] = "control_first", "control", "experiment"), IF(J223 = "Chat 2", IF(P01__1[[#This Row],[group]] = "control_first", "experiment", "control"), "")) | J223: Warmup
A224: 1 | B224: 1176110 | C224: 1177250 | E224: Jetzt kommt wieder die Ansicht. | F224: Speaker 1 | G224: =_xlfn.XLOOKUP(A224,participants!A:A,participants!C:C) -> control_first | H224: =IF(J224 = "Chat 1", IF(P01__1[[#This Row],[group]] = "control_first", "control", "experiment"), IF(J224 = "Chat 2", IF(P01__1[[#This Row],[group]] = "control_first", "experiment", "control"), "")) | J224: Warmup
A225: 1 | B225: 1177710 | C225: 1179210 | E225: Die mir vorher auch gut gefallen. | F225: Speaker 1 | G225: =_xlfn.XLOOKUP(A225,participants!A:A,participants!C:C) -> control_first | H225: =IF(J225 = "Chat 1", IF(P01__1[[#This Row],[group]] = "control_first", "control", "experiment"), IF(J225 = "Chat 2", IF(P01__1[[#This Row],[group]] = "control_first", "experiment", "control"), "")) | J225: Warmup
A226: 1 | B226: 1180590 | C226: 1181190 | E226: Ähm. | F226: Speaker 1 | G226: =_xlfn.XLOOKUP(A226,participants!A:A,participants!C:C) -> control_first | H226: =IF(J226 = "Chat 1", IF(P01__1[[#This Row],[group]] = "control_first", "control", "experiment"), IF(J226 = "Chat 2", IF(P01__1[[#This Row],[group]] = "control_first", "experiment", "control"), "")) | J226: Warmup
A227: 1 | B227: 1187560 | C227: 1188420 | E227: Du bist doll. | F227: Speaker 1 | G227: =_xlfn.XLOOKUP(A227,participants!A:A,participants!C:C) -> control_first | H227: =IF(J227 = "Chat 1", IF(P01__1[[#This Row],[group]] = "control_first", "control", "experiment"), IF(J227 = "Chat 2", IF(P01__1[[#This Row],[group]] = "control_first", "experiment", "control"), "")) | J227: Warmup
A228: 1 | B228: 1190520 | C228: 1191120 | E228: Muy contento. | F228: Speaker 1 | G228: =_xlfn.XLOOKUP(A228,participants!A:A,participants!C:C) -> control_first | H228: =IF(J228 = "Chat 1", IF(P01__1[[#This Row],[group]] = "control_first", "control", "experiment"), IF(J228 = "Chat 2", IF(P01__1[[#This Row],[group]] = "control_first", "experiment", "control"), "")) | J228: Warmup
A229: 1 | B229: 1191900 | C229: 1192300 | E229: Ah. | F229: Speaker 1 | G229: =_xlfn.XLOOKUP(A229,participants!A:A,participants!C:C) -> control_first | H229: =IF(J229 = "Chat 1", IF(P01__1[[#This Row],[group]] = "control_first", "control", "experiment"), IF(J229 = "Chat 2", IF(P01__1[[#This Row],[group]] = "control_first", "experiment", "control"), "")) | J229: Warmup
A230: 1 | B230: 1192580 | C230: 1192680 | E230: Ja. | F230: Speaker 1 | G230: =_xlfn.XLOOKUP(A230,participants!A:A,participants!C:C) -> control_first | H230: =IF(J230 = "Chat 1", IF(P01__1[[#This Row],[group]] = "control_first", "control", "experiment"), IF(J230 = "Chat 2", IF(P01__1[[#This Row],[group]] = "control_first", "experiment", "control"), "")) | J230: Warmup
A231: 1 | B231: 1192940 | C231: 1193120 | E231: Ja. | F231: Speaker 1 | G231: =_xlfn.XLOOKUP(A231,participants!A:A,participants!C:C) -> control_first | H231: =IF(J231 = "Chat 1", IF(P01__1[[#This Row],[group]] = "control_first", "control", "experiment"), IF(J231 = "Chat 2", IF(P01__1[[#This Row],[group]] = "control_first", "experiment", "control"), "")) | J231: Warmup
A232: 1 | B232: 1193200 | C232: 1193440 | E232: Okay. | F232: Speaker 1 | G232: =_xlfn.XLOOKUP(A232,participants!A:A,participants!C:C) -> control_first | H232: =IF(J232 = "Chat 1", IF(P01__1[[#This Row],[group]] = "control_first", "control", "experiment"), IF(J232 = "Chat 2", IF(P01__1[[#This Row],[group]] = "control_first", "experiment", "control"), "")) | J232: Warmup
A233: 1 | B233: 1193620 | C233: 1193820 | E233: Okay. | F233: Speaker 1 | G233: =_xlfn.XLOOKUP(A233,participants!A:A,participants!C:C) -> control_first | H233: =IF(J233 = "Chat 1", IF(P01__1[[#This Row],[group]] = "control_first", "control", "experiment"), IF(J233 = "Chat 2", IF(P01__1[[#This Row],[group]] = "control_first", "experiment", "control"), "")) | J233: Warmup
A234: 1 | B234: 1194940 | C234: 1195540 | E234: Verstehe. | F234: Speaker 1 | G234: =_xlfn.XLOOKUP(A234,participants!A:A,participants!C:C) -> control_first | H234: =IF(J234 = "Chat 1", IF(P01__1[[#This Row],[group]] = "control_first", "control", "experiment"), IF(J234 = "Chat 2", IF(P01__1[[#This Row],[group]] = "control_first", "experiment", "control"), "")) | J234: Warmup
... A277: 1 | B277: 1315690 | C277: 1316410 | E277: Me alegro. | F277: Speaker 1 | G277: =_xlfn.XLOOKUP(A277,participants!A:A,participants!C:C) -> control_first | H277: =IF(J277 = "Chat 1", IF(P01__1[[#This Row],[group]] = "control_first", "control", "experiment"), IF(J277 = "Chat 2", IF(P01__1[[#This Row],[group]] = "control_first", "experiment", "control"), "")) | J277: Warmup
A278: 1 | B278: 1317390 | C278: 1318510 | E278: Jetzt steht hier reconnecting. | F278: Speaker 1 | G278: =_xlfn.XLOOKUP(A278,participants!A:A,participants!C:C) -> control_first | H278: =IF(J278 = "Chat 1", IF(P01__1[[#This Row],[group]] = "control_first", "control", "experiment"), IF(J278 = "Chat 2", IF(P01__1[[#This Row],[group]] = "control_first", "experiment", "control"), "")) | J278: Warmup | L278: UX_Frustration
A279: 1 | B279: 1322180 | C279: 1322660 | E279: Okay. | F279: Speaker 1 | G279: =_xlfn.XLOOKUP(A279,participants!A:A,participants!C:C) -> control_first | H279: =IF(J279 = "Chat 1", IF(P01__1[[#This Row],[group]] = "control_first", "control", "experiment"), IF(J279 = "Chat 2", IF(P01__1[[#This Row],[group]] = "control_first", "experiment", "control"), "")) | J279: Warmup
A280: 1 | B280: 1322720 | C280: 1324140 | E280: Ich kann alles klicken. | F280: Speaker 2 | G280: =_xlfn.XLOOKUP(A280,participants!A:A,participants!C:C) -> control_first | H280: =IF(J280 = "Chat 1", IF(P01__1[[#This Row],[group]] = "control_first", "control", "experiment"), IF(J280 = "Chat 2", IF(P01__1[[#This Row],[group]] = "control_first", "experiment", "control"), "")) | J280: Warmup
A281: 1 | B281: 1327020 | C281: 1329300 | E281: Es kann irgendwas mit dem Internet vielleicht. | F281: Speaker 2 | G281: =_xlfn.XLOOKUP(A281,participants!A:A,participants!C:C) -> control_first | H281: =IF(J281 = "Chat 1", IF(P01__1[[#This Row],[group]] = "control_first", "control", "experiment"), IF(J281 = "Chat 2", IF(P01__1[[#This Row],[group]] = "control_first", "experiment", "control"), "")) | J281: Warmup
A282: 1 | B282: 1329300 | C282: 1334180 | E282: Weil eigentlich sollte es funktionieren. | F282: Speaker 2 | G282: =_xlfn.XLOOKUP(A282,participants!A:A,participants!C:C) -> control_first | H282: =IF(J282 = "Chat 1", IF(P01__1[[#This Row],[group]] = "control_first", "control", "experiment"), IF(J282 = "Chat 2", IF(P01__1[[#This Row],[group]] = "control_first", "experiment", "control"), "")) | J282: Warmup
A283: 1 | B283: 1335460 | C283: 1336660 | E283: Das könnte es sein. | F283: Speaker 1 | G283: =_xlfn.XLOOKUP(A283,participants!A:A,participants!C:C) -> control_first | H283: =IF(J283 = "Chat 1", IF(P01__1[[#This Row],[group]] = "control_first", "control", "experiment"), IF(J283 = "Chat 2", IF(P01__1[[#This Row],[group]] = "control_first", "experiment", "control"), "")) | J283: Warmup
A284: 1 | B284: 1336900 | C284: 1337400 | E284: Also ich hab. | F284: Speaker 1 | G284: =_xlfn.XLOOKUP(A284,participants!A:A,participants!C:C) -> control_first | H284: =IF(J284 = "Chat 1", IF(P01__1[[#This Row],[group]] = "control_first", "control", "experiment"), IF(J284 = "Chat 2", IF(P01__1[[#This Row],[group]] = "control_first", "experiment", "control"), "")) | J284: Warmup
A285: 1 | B285: 1337860 | C285: 1338820 | E285: Also dich höre ich ja noch. | F285: Speaker 1 | G285: =_xlfn.XLOOKUP(A285,participants!A:A,participants!C:C) -> control_first | H285: =IF(J285 = "Chat 1", IF(P01__1[[#This Row],[group]] = "control_first", "control", "experiment"), IF(J285 = "Chat 2", IF(P01__1[[#This Row],[group]] = "control_first", "experiment", "control"), "")) | J285: Warmup
A286: 1 | B286: 1339060 | C286: 1339440 | E286: Deswegen. | F286: Speaker 1 | G286: =_xlfn.XLOOKUP(A286,participants!A:A,participants!C:C) -> control_first | H286: =IF(J286 = "Chat 1", IF(P01__1[[#This Row],[group]] = "control_first", "control", "experiment"), IF(J286 = "Chat 2", IF(P01__1[[#This Row],[group]] = "control_first", "experiment", "control"), "")) | J286: Warmup
A287: 1 | B287: 1341980 | C287: 1345080 | E287: Soll ich irgendwie was testen? | F287: Speaker 1 | G287: =_xlfn.XLOOKUP(A287,participants!A:A,participants!C:C) -> control_first | H287: =IF(J287 = "Chat 1", IF(P01__1[[#This Row],[group]] = "control_first", "control", "experiment"), IF(J287 = "Chat 2", IF(P01__1[[#This Row],[group]] = "control_first", "experiment", "control"), "")) | J287: Warmup
A288: 1 | B288: 1345280 | C288: 1345880 | E288: Warte mal. | F288: Speaker 1 | G288: =_xlfn.XLOOKUP(A288,participants!A:A,participants!C:C) -> control_first | H288: =IF(J288 = "Chat 1", IF(P01__1[[#This Row],[group]] = "control_first", "control", "experiment"), IF(J288 = "Chat 2", IF(P01__1[[#This Row],[group]] = "control_first", "experiment", "control"), "")) | J288: Warmup
A289: 1 | B289: 1346300 | C289: 1349360 | E289: Sonst wenn du mal diese Konsole aufmachst. | F289: Speaker 2 | G289: =_xlfn.XLOOKUP(A289,participants!A:A,participants!C:C) -> control_first | H289: =IF(J289 = "Chat 1", IF(P01__1[[#This Row],[group]] = "control_first", "control", "experiment"), IF(J289 = "Chat 2", IF(P01__1[[#This Row],[group]] = "control_first", "experiment", "control"), "")) | J289: Warmup
A290: 1 | B290: 1350380 | C290: 1351000 | E290: Ja. | F290: Speaker 2 | G290: =_xlfn.XLOOKUP(A290,participants!A:A,participants!C:C) -> control_first | H290: =IF(J290 = "Chat 1", IF(P01__1[[#This Row],[group]] = "control_first", "control", "experiment"), IF(J290 = "Chat 2", IF(P01__1[[#This Row],[group]] = "control_first", "experiment", "control"), "")) | J290: Warmup
... A329: 1 | B329: 1445540 | C329: 1446020 | E329: Ähm. | F329: Speaker 1 | G329: =_xlfn.XLOOKUP(A329,participants!A:A,participants!C:C) -> control_first | H329: =IF(J329 = "Chat 1", IF(P01__1[[#This Row],[group]] = "control_first", "control", "experiment"), IF(J329 = "Chat 2", IF(P01__1[[#This Row],[group]] = "control_first", "experiment", "control"), "")) | J329: Warmup
A330: 1 | B330: 1450360 | C330: 1451800 | E330: Sagen wir ohne diese Tipps. Bin ich ein bisschen aufgeschmissen. Aber ich frage einfach. | F330: Speaker 1 | G330: =_xlfn.XLOOKUP(A330,participants!A:A,participants!C:C) -> control_first | H330: =IF(J330 = "Chat 1", IF(P01__1[[#This Row],[group]] = "control_first", "control", "experiment"), IF(J330 = "Chat 2", IF(P01__1[[#This Row],[group]] = "control_first", "experiment", "control"), "")) | J330: Warmup | L330: UX_Frustration
A331: 1 | B331: 1490600 | C331: 1492740 | E331: Vielleicht wenn ich dir noch einen Tipp geben kann. | F331: Speaker 2 | G331: =_xlfn.XLOOKUP(A331,participants!A:A,participants!C:C) -> control_first | H331: =IF(J331 = "Chat 1", IF(P01__1[[#This Row],[group]] = "control_first", "control", "experiment"), IF(J331 = "Chat 2", IF(P01__1[[#This Row],[group]] = "control_first", "experiment", "control"), "")) | J331: Warmup
...

Sheet participants
A1: ID | B1: uid | C1: Group
A2: 1 | B2: 3d3fad0c-f4e2-491f-97b3-95c71b7c6723 | C2: control_first
A3: 2 | B3: 700afe5f-e6dc-4191-9ffc-2d540d21780d | C3: experiment_first
A4: 3 | B4: 071b323f-15a1-4f26-8510-9a857540cf04 | C4: experiment_first
A5: 4 | B5: ecd6e48c-d160-4ad1-b576-772aee78a77a | C5: control_first
A6: 5 | B6: f21ef8da-e2e6-4a07-b757-2c2b8caa13df | C6: experiment_first
A7: 6 | B7: 2dbd9cc6-7d1f-4b50-9dc4-f22ba6c4aa09 | C7: control_first
A8: 7 | B8: 4ddbf84b-633f-49e1-9412-e52629d7eb1e | C8: experiment_first
A9: 8 | B9: 28ea6a5b-7ea9-41b2-851c-1317b0df0019 | C9: experiment_first
A10: 9 | B10: 05e5bd34-f2d8-4a3d-9453-e9f413cdfcf7 | C10: control_first
A11: 10 | B11: cd83ed7e-57d0-4ec5-8210-5acbbe5accae | C11: control_first
A12: 11 | B12: af32f0e9-f534-424a-9273-029dd49ac79f | C12: experiment_first
A13: 12 | B13: 71a109a5-6e81-44b3-b77f-531237e1c7d2 | C13: control_first
... A21: 20 | B21: 029df5a6-c0ca-41d9-8c3f-da05543cef44 | C21: control_first

Sheet observation_notes
A1: participant_id | B1: start | C1: end | D1: text | E1: speaker | F1: source_type | G1: main_phase | H1: sub_phase
A2: 1 | B2: 0 | C2: 0 | D2: Language level are clean | E2: Speaker 1 | F2: Observation Note | G2: Pre-Phase / General
A3: 1 | B3: 0 | C3: 0 | D3: Struggles: Which things do I select | E3: Speaker 1 | F3: Observation Note | G3: Pre-Phase / General
A4: 1 | B4: 0 | C4: 0 | D4: Makes bullet points in text field | E4: Speaker 1 | F4: Observation Note | G4: Pre-Phase / General
A5: 1 | B5: 0 | C5: 0 | D5: Nice to have the record button | E5: Speaker 1 | F5: Observation Note | G5: Warmup
A6: 1 | B6: 0 | C6: 0 | D6: Uses tutor if being lost | E6: Speaker 1 | F6: Observation Note | G6: Warmup
A7: 1 | B7: 0 | C7: 0 | D7: Was looking a bit to get out of tutor mode | E7: Speaker 1 | F7: Observation Note | G7: Warmup
A8: 1 | B8: 0 | C8: 0 | D8: Tends to ask the tutor as a quick fix for uncertain situations | E8: Speaker 1 | F8: Observation Note | G8: Warmup
A9: 1 | B9: 0 | C9: 0 | D9: Has the impression that AI is bad at referencing past messages | E9: Speaker 1 | F9: Observation Note | G9: Warmup
A10: 1 | B10: 0 | C10: 0 | D10: Tutor references the wrong message P. tried to just copy and paste the message | E10: Speaker 1 | F10: Observation Note | G10: Warmup
A11: 1 | B11: 0 | C11: 0 | D11: Likes the tutor, also the format | E11: Speaker 1 | F11: Observation Note | G11: Warmup
A12: 1 | B12: 0 | C12: 0 | D12: Uses tutor very intensely | E12: Speaker 1 | F12: Observation Note | G12: Warmup
A13: 1 | B13: 0 | C13: 0 | D13: Asks questions about pronunciation, which the ai can’t answer in audio | E13: Speaker 1 | F13: Observation Note | G13: Warmup
... A15: 1 | B15: 0 | C15: 0 | D15: AI misunderstood P. but he thought, that he mispronounced it | E15: Speaker 1 | F15: Observation Note | G15: Warmup
A16: 1 | B16: 0 | C16: 0 | D16: Really likes the hint function | E16: Speaker 1 | F16: Observation Note | G16: Warmup | H16: Partner explained something in Spanish instead of English
A17: 1 | B17: 0 | C17: 0 | D17: Does not understand the red highlight, what the mistake was | E17: Speaker 1 | F17: Observation Note | G17: Warmup | H17: Partner explained something in Spanish instead of English
A18: 1 | B18: 0 | C18: 0 | D18: Really likes that its spoken audio and that there are explanations in the partner message | E18: Speaker 1 | F18: Observation Note | G18: Warmup | H18: Partner explained something in Spanish instead of English
A19: 1 | B19: 0 | C19: 0 | D19: Tried to do it intuitively | E19: Speaker 1 | F19: Observation Note | G19: Warmup | H19: Think Aloud
A20: 1 | B20: 0 | C20: 0 | D20: Overread that he has to do the task | E20: Speaker 1 | F20: Observation Note | G20: Warmup | H20: Think Aloud
A21: 1 | B21: 0 | C21: 0 | D21: Doesn’t know how fast he could do it without the hint | E21: Speaker 1 | F21: Observation Note | G21: Warmup | H21: Think Aloud
A22: 1 | B22: 0 | C22: 0 | D22: When realizing there are hints, switched from tutor to using hints Were really good | E22: Speaker 1 | F22: Observation Note | G22: Warmup | H22: Think Aloud
A23: 1 | B23: 0 | C23: 0 | D23: Got into it after a few messages | E23: Speaker 1 | F23: Observation Note | G23: Warmup | H23: Think Aloud
A24: 1 | B24: 0 | C24: 0 | D24: Felt good: Corrections were woven into the responses, felt like he was learning with a partner | E24: Speaker 1 | F24: Observation Note | G24: Warmup | H24: Think Aloud
A25: 1 | B25: 0 | C25: 0 | D25: Tried to give it his own touch | E25: Speaker 1 | F25: Observation Note | G25: Warmup | H25: Think Aloud
A26: 1 | B26: 0 | C26: 0 | D26: Thought app crashed because of loading animation | E26: Speaker 1 | F26: Observation Note | G26: Warmup | H26: Summary
A27: 1 | B27: 0 | C27: 0 | D27: Like the cite | E27: Speaker 1 | F27: Observation Note | G27: Warmup | H27: Summary
... A33: 1 | B33: 0 | C33: 0 | D33: But reading the updates feels a bit frustrating to see, because it lists so many weak points | E33: Speaker 1 | F33: Observation Note | G33: Warmup | H33: Summary
A34: 1 | B34: 0 | C34: 0 | D34: Wanted to check the hint, but oversaw that now it’s the solution | E34: Speaker 1 | F34: Observation Note | G34: Chat 1
A35: 1 | B35: 0 | C35: 0 | D35: Tends to use the hint when unsure | E35: Speaker 1 | F35: Observation Note | G35: Chat 1
A36: 1 | B36: 0 | C36: 0 | D36: Ai skipped one task, then the AI continued but was confused | E36: Speaker 1 | F36: Observation Note | G36: Chat 1
A37: 1 | B37: 0 | C37: 0 | D37: Tends to use only the hint/solution without adding extra content | E37: Speaker 1 | F37: Observation Note | G37: Chat 1
A38: 1 | B38: 0 | C38: 0 | D38: Reads the summary very carefully | E38: Speaker 1 | F38: Observation Note | G38: Chat 1 | H38: Summary
A39: 1 | B39: 0 | C39: 0 | D39: Connection issue in the beginning of the convo | E39: Speaker 1 | F39: Observation Note | G39: Chat 2
A40: 1 | B40: 0 | C40: 0 | D40: Got a personalized explanation | E40: Speaker 1 | F40: Observation Note | G40: Chat 2 | H40: Partner made a joke, P. had to laugh
A41: 1 | B41: 0 | C41: 0 | D41: Reconnection error | E41: Speaker 1 | F41: Observation Note | G41: Chat 2 | H41: Partner made a joke, P. had to laugh
A42: 1 | B42: 0 | C42: 0 | D42: For abblino: | E42: Speaker 1 | F42: Observation Note | G42: Chat 2 | H42: Partner made a joke, P. had to laugh
A43: 1 | B43: 0 | C43: 0 | D43: Always have pronunciation option for all messages | E43: Speaker 1 | F43: Observation Note | G43: Chat 2 | H43: Partner made a joke, P. had to laugh
A44: 1 | B44: 0 | C44: 0 | D44: Hint feature | E44: Speaker 1 | F44: Observation Note | G44: Chat 2 | H44: Partner made a joke, P. had to laugh
A45: 1 | B45: 0 | C45: 0 | D45: Offer a translation of the messages | E45: Speaker 1 | F45: Observation Note | G45: Chat 2 | H45: Partner made a joke, P. had to laugh
A46: 2 | B46: 0 | C46: 0 | D46: Likes the design | E46: Speaker 1 | F46: Observation Note | G46: Onboarding
A47: 2 | B47: 0 | C47: 0 | D47: Lots of text @level | E47: Speaker 1 | F47: Observation Note | G47: Onboarding
A48: 2 | B48: 0 | C48: 0 | D48: Likes the progress bar | E48: Speaker 1 | F48: Observation Note | G48: Onboarding
A49: 2 | B49: 0 | C49: 0 | D49: Likes that the app asks his struggles | E49: Speaker 1 | F49: Observation Note | G49: Onboarding
A50: 2 | B50: 0 | C50: 0 | D50: Likes that its an age range | E50: Speaker 1 | F50: Observation Note | G50: Onboarding
A51: 2 | B51: 0 | C51: 0 | D51: Likes the partner customization | E51: Speaker 1 | F51: Observation Note | G51: Onboarding | H51: Partner
A52: 2 | B52: 0 | C52: 0 | D52: Taps on play button but no sound | E52: Speaker 1 | F52: Observation Note | G52: Onboarding | H52: Partner
A53: 2 | B53: 0 | C53: 0 | D53: Warm-up: | E53: Speaker 1 | F53: Observation Note | G53: Onboarding | H53: Partner
A54: 2 | B54: 0 | C54: 0 | D54: Audio understanding had difficulties from background noise | E54: Speaker 1 | F54: Observation Note | G54: Onboarding | H54: Partner
A55: 2 | B55: 0 | C55: 0 | D55: Wanted to use text input | E55: Speaker 1 | F55: Observation Note | G55: Onboarding | H55: Partner
A56: 2 | B56: 0 | C56: 0 | D56: Would be nice to still see tutor responds in normal chat, otherwise you have to memorize what he said | E56: Speaker 1 | F56: Observation Note | G56: Onboarding | H56: Partner
A57: 2 | B57: 0 | C57: 0 | D57: Would be nice to have voice input in the tutor mode | E57: Speaker 1 | F57: Observation Note | G57: Onboarding | H57: Partner
A58: 2 | B58: 0 | C58: 0 | D58: Common flow: Partner response Ask tutor how to respond Say answer | E58: Speaker 1 | F58: Observation Note | G58: Onboarding | H58: Partner
A59: 2 | B59: 0 | C59: 0 | D59: Noticed that the speech recognition continue when toggling tutor mode | E59: Speaker 1 | F59: Observation Note | G59: Onboarding | H59: Partner
A60: 2 | B60: 0 | C60: 0 | D60: Can’t scroll up the chat Bad UX | E60: Speaker 1 | F60: Observation Note | G60: Onboarding | H60: Partner
A61: 2 | B61: 0 | C61: 0 | D61: Voice sounds very natural Likes it very much | E61: Speaker 1 | F61: Observation Note | G61: Onboarding | H61: Partner
A62: 2 | B62: 0 | C62: 0 | D62: Asks if he can see the mistake explanations in the chat | E62: Speaker 1 | F62: Observation Note | G62: Onboarding | H62: Partner
... A72: 2 | B72: 0 | C72: 0 | D72: Important: Thought that there were 10 tasks in the menu | E72: Speaker 1 | F72: Observation Note | G72: Onboarding | H72: Summary
A73: 2 | B73: 0 | C73: 0 | D73: Likes that the tutor used his name | E73: Speaker 1 | F73: Observation Note | G73: Chat 1
A74: 2 | B74: 0 | C74: 0 | D74: Finds it very motivating that the STT is very accurate and high performance | E74: Speaker 1 | F74: Observation Note | G74: Chat 1
A75: 2 | B75: 0 | C75: 0 | D75: Would be nice to see what the tutor recommended to say | E75: Speaker 1 | F75: Observation Note | G75: Chat 1 | H75: Partner sometimes gives the tutor tip in Spanish instead of English Then P. uses the tutor to ask what he said
A76: 2 | B76: 0 | C76: 0 | D76: Noticed the task list view only by accident Is not obvious | E76: Speaker 1 | F76: Observation Note | G76: Chat 1 | H76: Partner tends to say Moritz in every message
A77: 2 | B77: 0 | C77: 0 | D77: Tends to open the hint/solution while recording the audio to read from the hints | E77: Speaker 1 | F77: Observation Note | G77: Chat 2
A78: 2 | B78: 0 | C78: 0 | D78: Says he really likes it and feels like he makes progress | E78: Speaker 1 | F78: Observation Note | G78: Chat 2
A79: 2 | B79: 0 | C79: 0 | D79: Doesn’t make so many mistakes because he uses the hints/tutor mode | E79: Speaker 1 | F79: Observation Note | G79: Chat 2 | H79: Partner gave an in depth correction
A80: 3 | B80: 0 | C80: 0 | D80: Asks if the level is what she has on paper or how she would rate herself now | E80: Speaker 1 | F80: Observation Note | G80: Onboarding
A81: 3 | B81: 0 | C81: 0 | D81: Creates someone that looks like her | E81: Speaker 1 | F81: Observation Note | G81: Onboarding | H81: Partner
A82: 3 | B82: 0 | C82: 0 | D82: Reconnecting issue | E82: Speaker 1 | F82: Observation Note | G82: Warmup
A83: 3 | B83: 0 | C83: 0 | D83: Is unsure if she has to press to record | E83: Speaker 1 | F83: Observation Note | G83: Warmup
A84: 3 | B84: 0 | C84: 0 | D84: Very fast answer, was almost shocked | E84: Speaker 1 | F84: Observation Note | G84: Warmup
A85: 3 | B85: 0 | C85: 0 | D85: Voice sounded very natural and fluent | E85: Speaker 1 | F85: Observation Note | G85: Warmup
A86: 3 | B86: 0 | C86: 0 | D86: Did not recognize that she solved the task | E86: Speaker 1 | F86: Observation Note | G86: Warmup
A87: 3 | B87: 0 | C87: 0 | D87: Really liked that the partner corrected her, meta cognitively | E87: Speaker 1 | F87: Observation Note | G87: Warmup | H87: Partner showed hole context
A88: 3 | B88: 0 | C88: 0 | D88: Giving alternatives and the use case for them | E88: Speaker 1 | F88: Observation Note | G88: Warmup | H88: Partner showed hole context
A89: 3 | B89: 0 | C89: 0 | D89: The immediate answer was very helpful | E89: Speaker 1 | F89: Observation Note | G89: Warmup | H89: Partner showed hole context
A90: 3 | B90: 0 | C90: 0 | D90: Really liked the text highlights | E90: Speaker 1 | F90: Observation Note | G90: Warmup | H90: Partner showed hole context
A91: 3 | B91: 0 | C91: 0 | D91: What does words learned mean | E91: Speaker 1 | F91: Observation Note | G91: Warmup | H91: Summary
A92: 3 | B92: 0 | C92: 0 | D92: Likes the vocabulary list | E92: Speaker 1 | F92: Observation Note | G92: Warmup | H92: Summary
A93: 3 | B93: 0 | C93: 0 | D93: Very clean and structured | E93: Speaker 1 | F93: Observation Note | G93: Warmup | H93: Summary
A94: 3 | B94: 0 | C94: 0 | D94: Likes that the mistakes are explained | E94: Speaker 1 | F94: Observation Note | G94: Warmup | H94: Summary
A95: 3 | B95: 0 | C95: 0 | D95: Memory: | E95: Speaker 1 | F95: Observation Note | G95: Warmup | H95: Summary
A96: 3 | B96: 0 | C96: 0 | D96: Feels like its notes | E96: Speaker 1 | F96: Observation Note | G96: Warmup | H96: Summary
A97: 3 | B97: 0 | C97: 0 | D97: Likes that its structured and that its too much text, not overwhelming | E97: Speaker 1 | F97: Observation Note | G97: Warmup | H97: Summary
A98: 3 | B98: 0 | C98: 0 | D98: Looks at task list carefully | E98: Speaker 1 | F98: Observation Note | G98: Chat 1
A99: 3 | B99: 0 | C99: 0 | D99: Did not recognize the second task/didn’t do the task | E99: Speaker 1 | F99: Observation Note | G99: Chat 1
A100: 3 | B100: 0 | C100: 0 | D100: Maybe task list is too subtle? | E100: Speaker 1 | F100: Observation Note | G100: Chat 1
A101: 3 | B101: 0 | C101: 0 | D101: Tends to immerse in the chat instead of following the task list strictly | E101: Speaker 1 | F101: Observation Note | G101: Chat 2
A102: 3 | B102: 0 | C102: 0 | D102: Did not complete all tasks then tries to do them after saying goodbye | E102: Speaker 1 | F102: Observation Note | G102: Chat 2
A103: 4 | B103: 0 | C103: 0 | D103: Skin color: Finds it strange to select skin color, because she doesn’t care | E103: Speaker 1 | F103: Observation Note | G103: Onboarding
A104: 4 | B104: 0 | C104: 0 | D104: Seemed a bit confused | E104: Speaker 1 | F104: Observation Note | G104: Onboarding
A105: 4 | B105: 0 | C105: 0 | D105: Tries to click the voice button at the voice input | E105: Speaker 1 | F105: Observation Note | G105: Onboarding
A106: 4 | B106: 0 | C106: 0 | D106: Name: SpansihBuddy: Says its very uncreative | E106: Speaker 1 | F106: Observation Note | G106: Onboarding
A107: 4 | B107: 0 | C107: 0 | D107: Warm-Up: | E107: Speaker 1 | F107: Observation Note | G107: Onboarding
A108: 4 | B108: 0 | C108: 0 | D108: Tries help immediately | E108: Speaker 1 | F108: Observation Note | G108: Onboarding
A109: 4 | B109: 0 | C109: 0 | D109: Asks the tutor for approval of what she want to say | E109: Speaker 1 | F109: Observation Note | G109: Onboarding
... A114: 4 | B114: 0 | C114: 0 | D114: Feel like the AI doesn’t get everything correctly Issues with STT | E114: Speaker 1 | F114: Observation Note | G114: Onboarding
A115: 4 | B115: 0 | C115: 0 | D115: AI spoke too fast Especially because she is a bigger | E115: Speaker 1 | F115: Observation Note | G115: Onboarding | H115: Summary very long loading time
A116: 4 | B116: 0 | C116: 0 | D116: Would prefer to have shorter scenarios | E116: Speaker 1 | F116: Observation Note | G116: Onboarding | H116: Summary very long loading time
A117: 4 | B117: 0 | C117: 0 | D117: Was lost what to do | E117: Speaker 1 | F117: Observation Note | G117: Onboarding | H117: Summary very long loading time
A118: 4 | B118: 0 | C118: 0 | D118: But really liked the feedback in the response | E118: Speaker 1 | F118: Observation Note | G118: Onboarding | H118: Summary very long loading time
A119: 4 | B119: 0 | C119: 0 | D119: Overlooked the other tabs | E119: Speaker 1 | F119: Observation Note | G119: Onboarding | H119: Summary very long loading time
...

Sheet P20
A1: start | B1: end | C1: text | D1: speaker
A2: 1160 | B2: 1800 | C2: Hallo. | D2: Speaker 2
A3: 2240 | B3: 2520 | C3: Okay. | D3: Speaker 1
A4: 2880 | B4: 3560 | C4: Okay, super. | D4: Speaker 1
A5: 3680 | B5: 4160 | C5: Es klingt auf. | D5: Speaker 1
A6: 4620 | B6: 4820 | C6: Genau. | D6: Speaker 1
A7: 4980 | B7: 14960 | C7: Erstmal, bevor wir anfangen, danke, dass du dir die Zeit nimmst, heute teilzunehmen und das Interview dauert so 45 bis 60 Minuten. | D7: Speaker 1
A8: 16480 | B8: 23300 | C8: Das Interview wird aufgezeichnet und ist dann später zu transkribieren und die Aufzeichnung wird dann nach der Transkription gelöscht. | D8: Speaker 1
A9: 23840 | B9: 31479 | C9: Du kannst auch jederzeit das Interview stoppen oder deine Einverständniserklärung entziehen, ohne irgendwelche Gründe zu nennen oder Nachteile zu empfangen. | D9: Speaker 1
A10: 32280 | B10: 34740 | C10: Deswegen einmal die Frage, ob du damit einverstanden bist. | D10: Speaker 1
A11: 35340 | B11: 35500 | C11: Ja. | D11: Speaker 1
A12: 35940 | B12: 36420 | C12: Okay, super. | D12: Speaker 1
A13: 37180 | B13: 38720 | C13: Dann nochmal kurz zur Struktur. | D13: Speaker 1
... A748: 4081180 | B748: 4083000 | C748: Dann beende ich einmal die Aufnahme. | D748: Speaker 1

Sheet P19
A1: start | B1: end | C1: text | D1: speaker
A2: 0 | B2: 3390 | C2: Gesamter Bildschirm, Bildschirm 1. | D2: Speaker 1
A3: 8920 | B3: 10240 | C3: Okay, perfekt. | D3: Speaker 1
A4: 12000 | B4: 15720 | C4: Genau, ich habe in den Chats die beiden Links geschickt. | D4: Speaker 1
A5: 16020 | B5: 18280 | C5: Einmal für die App. | D5: Speaker 1
A6: 20500 | B6: 21340 | C6: Wo sehen wir denn den Chat? | D6: Speaker 1
A7: 22940 | B7: 24520 | C7: Ich glaube, der ist da. | D7: Speaker 1
A8: 25380 | B8: 26340 | C8: Wo ist denn der bei dir? | D8: Speaker 1
A9: 27840 | B9: 29940 | C9: Bei weiterer Option vielleicht. | D9: Speaker 1
A10: 30000 | B10: 30760 | C10: Ah ne, da unten. | D10: Speaker 1
A11: 35130 | B11: 37750 | C11: Genau, der untere ist der Fragebogen. | D11: Speaker 1
A12: 38410 | B12: 40290 | C12: Dann sage ich dir aber nochmal Bescheid. | D12: Speaker 1
A13: 40810 | B13: 41270 | C13: Erste, oder? | D13: Speaker 1
... A1071: 5654570 | B1071: 5654710 | C1071: Vielen Dank. | D1071: Speaker 1

Sheet P18
A1: start | B1: end | C1: text | D1: speaker
A2: 880 | B2: 6560 | C2: Bevor du weitermachst, ich hab noch mal so ein kleines Skript, das würde ich einmal durchgehen, und dann... | D2: Speaker 2
A3: 8120 | B3: 8480 | C3: Moment. | D3: Speaker 2
A4: 11530 | B4: 14970 | C4: Jetzt wollte ich nur gerade mal gucken, wie ich das hier anders anordnen kann. | D4: Speaker 2
A5: 34590 | B5: 34690 | C5: Okay. | D5: Speaker 2
A6: 35550 | B6: 36450 | C6: Machst du so wahrscheinlich? | D6: Speaker 2
A7: 37090 | B7: 37930 | C7: Ja, perfekt, okay. | D7: Speaker 2
A8: 38810 | B8: 39710 | C8: Ähm, okay, super. | D8: Speaker 2
A9: 40490 | B9: 40850 | C9: Dann... | D9: Speaker 2
A10: 40850 | B10: 43310 | C10: Genau, ich hab hier so ein kleines Skript, ich schreib's so nebenbei einfach mit. | D10: Speaker 2
A11: 44190 | B11: 46950 | C11: Äh, aber erst mal danke dir nochmal, dass du dir die Zeit nimmst. | D11: Speaker 2
A12: 47470 | B12: 50050 | C12: Und die Studie dauert so 45 bis 60 Minuten. | D12: Speaker 2
A13: 50910 | B13: 51390 | C13: Okay. | D13: Speaker 2
... A761: 5545360 | B761: 5546840 | C761: Dann beende ich einmal die Aufnahme. | D761: Speaker 2

Sheet P17
A1: start | B1: end | C1: text | D1: speaker
A2: 710 | B2: 1830 | C2: Genau, okay. | D2: Speaker 2
A3: 2330 | B3: 10170 | C3: Genau, dann nochmal danke dir, dass du dir heute die Zeit nimmst und ich habe hier noch so ein kleines Skript, also nicht, dass du dich wunderst. | D3: Speaker 2
A4: 10270 | B4: 11490 | C4: Ich gehe das einmal durch. | D4: Speaker 2
A5: 12190 | B5: 29830 | C5: Also die Studie dauert so 45 bis 60 Minuten und das Interview wird aufgezeichnet, um das dann später zu transkribieren und die Aufnahme wird dann nach der Transkription gelöscht und du kannst auch jederzeit das Interview anhalten oder deine Einverständnis entziehen, ohne irgendwelche Gründe zu nennen oder Nachteile zu erfahren. | D5: Speaker 2
A6: 30430 | B6: 32890 | C6: Deswegen einmal die Frage, ob du damit einverstanden bist. | D6: Speaker 2
A7: 33750 | B7: 33870 | C7: Ja. | D7: Speaker 1
A8: 34610 | B8: 35110 | C8: Okay, super. | D8: Speaker 2
A9: 35670 | B9: 37210 | C9: Genau, dann nochmal kurz zur Struktur. | D9: Speaker 2
A10: 37910 | B10: 48850 | C10: Also gleich, wenn du in der App bist, hast du erstmal so ein kleines Onboarding, wo du dann zum Beispiel dein Sprachlevel angibst und so weiter und danach hast du dann drei Konversationen. | D10: Speaker 2
A11: 48850 | B11: 51850 | C11: Die erste Konversation, da wird eigentlich noch | D11: Speaker 2
A12: 51850 | B12: 55470 | C12: nichts gemessen und es geht erstmal nur darum, dass du so ein bisschen dich mit | D12: Speaker 2
A13: 55470 | B13: 58410 | C13: dem System vertraut machen kannst und so ein bisschen gucken kannst, wie das | D13: Speaker 2
... A482: 3602290 | B482: 3603370 | C482: Kann er auch Spanisch? | D482: Speaker 1

Sheet P16
A1: start | B1: end | C1: text | D1: speaker
A2: 720 | B2: 1460 | C2: Aufnahmebeginn, genau. | D2: Speaker 2
A3: 2560 | B3: 8480 | C3: Und ich habe hier so ein kleines Interviewleitfaden, also nicht, dass du dich wunderst, wenn ich mal hier so ein bisschen schreibe. | D3: Speaker 2
A4: 10360 | B4: 14000 | C4: Genau, dann also nochmal danke dir, dass du dir heute die Zeit nimmst. | D4: Speaker 2
A5: 14860 | B5: 15000 | C5: Sehr gerne. | D5: Speaker 2
A6: 15000 | B6: 18480 | C6: Und die Studie dauert so ungefähr 45 bis 60 Minuten. | D6: Speaker 2
A7: 19220 | B7: 32780 | C7: Das Interview wird aufgezeichnet, um das dann später zu transkribieren und die Audio wird dann nach der Transkription gelöscht und du kannst auch jederzeit das Interview anhalten oder deine Einverständnis entziehen, ohne Gründe zu nennen oder irgendwelche Nachteile zu bekommen. | D7: Speaker 2
A8: 33260 | B8: 35520 | C8: Deswegen einmal die Frage, ob du damit einverstanden bist. | D8: Speaker 2
A9: 35760 | B9: 36020 | C9: Klar. | D9: Speaker 1
A10: 36900 | B10: 39160 | C10: Bist du denn jetzt hier live dabei, wenn ich das mache? | D10: Speaker 1
A11: 39800 | B11: 40860 | C11: Genau, genau, ich bin live dabei. | D11: Speaker 2
A12: 42580 | B12: 44260 | C12: Warum hast du das auf Englisch? | D12: Speaker 1
A13: 44460 | B13: 45500 | C13: How should we call you? | D13: Speaker 1
... A715: 4204330 | B715: 4206190 | C715: Dann beende ich einmal die Aufnahme. | D715: Speaker 2

Sheet P15
A1: start | B1: end | C1: text | D1: speaker
A2: 840 | B2: 2960 | C2: Genau, okay, super. | D2: Speaker 1
A3: 3340 | B3: 5220 | C3: Dann danke dir nochmal, dass du dir die Zeit nimmst. | D3: Speaker 1
A4: 5380 | B4: 14840 | C4: Die Studie dauert so 45 bis 60 Minuten und das Interview wird aufgezeichnet, um das dann später zu transkribieren und die Aufnahme wird auch nach der Transkription gelöscht. | D4: Speaker 1
A5: 15140 | B5: 21800 | C5: Du kannst jederzeit das Interview anhalten oder deine Einwilligung entziehen, ohne irgendwelche Gründe zu nennen oder Nachteile zu erfahren. | D5: Speaker 1
A6: 22940 | B6: 25160 | C6: Deswegen einmal die Frage, ob du damit einverstanden bist. | D6: Speaker 1
A7: 26180 | B7: 27240 | C7: Ich bin einverstanden. | D7: Speaker 1
A8: 27740 | B8: 28600 | C8: Okay, perfekt. | D8: Speaker 1
A9: 29360 | B9: 30860 | C9: Genau, dann nochmal kurz zum Aufbau. | D9: Speaker 1
A10: 31000 | B10: 38280 | C10: Also du hast jetzt gleich, wenn du auf Start Study klickst, ein kleines Onboarding, wo du so ein paar Daten über dich angibst. | D10: Speaker 1
A11: 38280 | B11: 41300 | C11: Dann hast du drei Konversationen. | D11: Speaker 1
A12: 41400 | B12: 46700 | C12: Einmal diese Warm-up-Konversation und dann jeweils eine oder zwei weitere Konversationen. | D12: Speaker 1
A13: 46820 | B13: 49020 | C13: Und am Ende stelle ich dann noch ein paar Fragen. | D13: Speaker 1
... A476: 4475710 | B476: 4479830 | C476: Dann danke dir für deine Teilnahme und dann beende ich einmal die Aufnahme. | D476: Speaker 1

Sheet P14
A1: start | B1: end | C1: text | D1: speaker
A2: 140 | B2: 24220 | C2: Genau, dann nochmal danke dir, dass du dir die Zeit nimmst und die Studie dauert so ungefähr 45 bis 60 Minuten und das Interview wird aufgezeichnet, um das dann später zu transkribieren und die Aufnahme wird dann nach der Transkription gelöscht und du kannst auch jederzeit das Interview anhalten oder deine Einverständnis entziehen, ohne Gründe zu nennen oder irgendwelche Nachteile zu erfahren. | D2: Speaker 1
A3: 24720 | B3: 27240 | C3: Deswegen einmal die Frage, ob du damit einverstanden bist? | D3: Speaker 1
A4: 27240 | B4: 28480 | C4: Ja. | D4: Speaker 1
A5: 57240 | B5: 78440 | C5: Nee. | D5: Speaker 1
A6: 78440 | B6: 79980 | C6: Okay, kein Problem. | D6: Speaker 1
A7: 80360 | B7: 94000 | C7: Genau, also das muss man sich so vorstellen, eigentlich wie so der Kommentator deiner Gedanken, also dass du quasi die Gedanken, die du während der Interaktion hast, laut aussprechen kannst. | D7: Speaker 1
A8: 95200 | B8: 108160 | C8: Also das hilft dann zum Beispiel mir dabei herauszufinden, wo vielleicht Punkte in der App sind, die noch nicht so gut funktionieren oder wo dann die Nutzer irritiert sind oder was anderes erwarten. | D8: Speaker 1
A9: 109500 | B9: 113720 | C9: Und genau, du kannst aber … | D9: Speaker 1
A10: 113720 | B10: 116360 | C10: Also ich soll eigentlich meine Gedanken laut aussprechen? | D10: Speaker 2
A11: 116360 | B11: 117500 | C11: Genau, genau. | D11: Speaker 1
A12: 118700 | B12: 127639 | C12: Nur bei der ersten Konversation habe ich auch öfter gemerkt, dass manchmal ist das ein bisschen überfordernd, dann irgendwie gleichzeitig Spanisch und dann auf Deutsch irgendwie die Gedanken sagen. | D12: Speaker 1
A13: 128120 | B13: 135900 | C13: Deswegen, wenn du merkst, das ist dann doch irgendwie zu viel, ist das gar kein Problem, dann können wir das so im Nachhinein machen. | D13: Speaker 1
... A406: 4286880 | B406: 4289320 | C406: Und dann beende ich einmal die Aufnahme. | D406: Speaker 1

Sheet P13
A1: start | B1: end | C1: text | D1: speaker
A2: 1900 | B2: 9000 | C2: Also nochmal danke für deine Teilnahme und die Studie dauert so ungefähr 45 bis 60 Minuten. | D2: Speaker 1
A3: 10380 | B3: 18640 | C3: Das Interview wird aufgezeichnet, um das dann später zu transkribieren und die Aufnahme wird dann nach der Transkription gelöscht. | D3: Speaker 1
A4: 18820 | B4: 26660 | C4: Und du kannst auch jederzeit das Interview anhalten oder deine Einverständniserklärung entziehen, ohne irgendwelche Gründe zu nennen oder Nachteile zu erfahren. | D4: Speaker 1
A5: 26660 | B5: 29720 | C5: Deswegen einmal die Frage, ob du damit einverstanden bist. | D5: Speaker 1
A6: 30760 | B6: 32380 | C6: Ja, ich bin damit einverstanden. | D6: Speaker 1
A7: 33140 | B7: 33860 | C7: Okay, perfekt. | D7: Speaker 1
A8: 34580 | B8: 36480 | C8: Genau, dann nochmal zur Struktur. | D8: Speaker 1
A9: 36700 | B9: 41660 | C9: Also du hast gleich so ein kleines Onboarding, wo du durchgehst und dann danach hast du drei Konversationen. | D9: Speaker 1
A10: 42340 | B10: 44640 | C10: Die erste ist so eine Art Warm-up-Konversation. | D10: Speaker 1
A11: 44780 | B11: 50660 | C11: Das heißt, da kannst du quasi ganz entspannt erstmal die App ausprobieren, dich so ein bisschen zurechtfinden. | D11: Speaker 1
A12: 52020 | B12: 55660 | C12: Und dann quasi zwei weitere Konversationen. | D12: Speaker 1
A13: 56520 | B13: 58260 | C13: Und danach würde ich noch ein paar Fragen stellen. | D13: Speaker 1
... A860: 5782870 | B860: 5786970 | C860: Dann danke dir für deine Teilnahme und dann beende ich einmal die Aufnahme. | D860: Speaker 1

Sheet P12
A1: start | B1: end | C1: text | D1: speaker
A2: 970 | B2: 7710 | C2: Und dann öffne ich noch einmal mein Skript, Moment. | D2: Speaker 1
A3: 9960 | B3: 19500 | C3: Muss ich jetzt auf diese andere App, also auf diese Conversation Language Learning, also fangen wir erst damit an und dann auf Next, also weiterklicken, oder? | D3: Speaker 1
A4: 20240 | B4: 25180 | C4: Die ist noch nicht relevant, also da musst du noch nichts machen. | D4: Speaker 1
A5: 25560 | B5: 29640 | C5: Das ist nur ein Fragebogen, weil du hast ja drei Konversationen. | D5: Speaker 1
A6: 29640 | B6: 34420 | C6: Nach der zweiten und dritten würde ich dich bitten, dann einmal den Fragebogen auszufüllen. | D6: Speaker 1
A7: 38940 | B7: 40820 | C7: Okay, also hiermit machen wir jetzt erst mal weiter. | D7: Speaker 1
A8: 41920 | B8: 47960 | C8: Genau, also mit der, ich weiß gerade nicht auf welchen, bist du auf der App drauf? | D8: Speaker 1
A9: 48860 | B9: 49520 | C9: Ja, perfekt. | D9: Speaker 1
A10: 50380 | B10: 50640 | C10: Okay. | D10: Speaker 1
A11: 51500 | B11: 52300 | C11: Ja, ja. | D11: Speaker 1
A12: 53380 | B12: 53940 | C12: Okay, super. | D12: Speaker 1
A13: 54540 | B13: 57840 | C13: Genau, dann danke dir nochmal, dass du hier teilnimmst. | D13: Speaker 1
... A472: 3909010 | B472: 3912470 | C472: Dann danke dir für deine Teilnahme und ich beende einmal die Aufnahme. | D472: Speaker 1

Sheet P11
A1: start | B1: end | C1: text | D1: speaker
A2: 0 | B2: 18720 | C2: Okay, dann nochmal danke dir, dass du dir die Zeit genommen hast und das Interview oder die Studie dauert so 45 bis 60 Minuten und das Interview wird aufgezeichnet, um das dann später zu transkribieren und die Audio wird dann nach der Transkription gelöfft. | D2: Speaker 2
A3: 18800 | B3: 26500 | C3: Du kannst auch jederzeit das Interview anhalten oder deine Einverständniserklärung entziehen, ohne Gründe zu nennen oder irgendwelche Nachteile zu bekommen. | D3: Speaker 2
A4: 27080 | B4: 29560 | C4: Deswegen einmal die Frage, ob du damit einverstanden bist. | D4: Speaker 2
A5: 30360 | B5: 31159 | C5: Ja, bin ich. | D5: Speaker 2
A6: 31980 | B6: 32640 | C6: Okay, perfekt. | D6: Speaker 2
A7: 33120 | B7: 34560 | C7: Genau, dann nochmal kurz zur Struktur. | D7: Speaker 2
A8: 34840 | B8: 40720 | C8: Also, du bist ja jetzt schon auf der App und du hast jetzt gleich erstmal so ein kleines Onboarding. | D8: Speaker 2
A9: 41520 | B9: 44760 | C9: Dann hast du drei Konversationen. | D9: Speaker 2
A10: 45100 | B10: 54240 | C10: Die erste Konversation ist quasi eine Warm-up-Konversation, das heißt, da kannst du dich erstmal mit dem ganzen System vertraut machen und das ist quasi ganz entspannt. | D10: Speaker 2
A11: 54860 | B11: 64379 | C11: Und dann jeweils noch zwei weitere Konversationen und am Ende dann nochmal ein paar tiefergehende Fragen. | D11: Speaker 2
A12: 67500 | B12: 76920 | C12: Und nach der zweiten und dritten Konversation würde ich dich dann bitten, den Fragebogen auszufüllen für die beiden Konversationen, aber da sage ich dir dann noch Bescheid. | D12: Speaker 2
A13: 78400 | B13: 86620 | C13: Genau, und ich würde bei der Warm-up-Konversation die Think-Aloud-Methode anwenden. | D13: Speaker 2
... A833: 4696550 | B833: 4702690 | C833: Okay, dann danke dir für deine Teilnahme und dann beende ich einmal die Aufnahme. | D833: Speaker 2

Sheet P10
A1: start | B1: end | C1: text | D1: speaker
A2: 1440 | B2: 3840 | C2: Okay, perfekt. | D2: Speaker 1
A3: 3960 | B3: 10560 | C3: Genau, dann nochmal danke dir, dass du dir die Zeit nimmst heute und die Nutzerstudie dauert so 45 bis 60 Minuten. | D3: Speaker 1
A4: 11440 | B4: 26540 | C4: Das Interview wird aufgezeichnet, um das dann später zu transkribieren und die Audio wird dann nach der Transkription gelöscht und du kannst auch jederzeit das Interview anhalten oder deine Einwilligungserklärung entziehen, ohne Gründe zu nennen oder irgendwelche Nachteile zu erfahren. | D4: Speaker 1
A5: 27100 | B5: 29480 | C5: Deswegen einmal die Frage, ob du damit einverstanden bist. | D5: Speaker 1
A6: 30980 | B6: 32060 | C6: Ja, ich bin einverstanden. | D6: Speaker 1
A7: 32620 | B7: 33280 | C7: Okay, perfekt. | D7: Speaker 1
A8: 34140 | B8: 36540 | C8: Genau, dann nochmal kurz zur Struktur. | D8: Speaker 1
A9: 37220 | B9: 47380 | C9: Also, du hast gleich, wenn du jetzt in der App bist, musst du ein kleines Onboarding machen, wo ein paar Fragen über dich gestellt werden und dann hast du drei Konversationen. | D9: Speaker 1
A10: 48000 | B10: 51160 | C10: Die erste Konversation ist eine Art Warm-Up. | D10: Speaker 1
A11: 51800 | B11: 62100 | C11: Das heißt, da kannst du dich erstmal so ein bisschen ins System reinfuchsen, ausprobieren und einfach so ein bisschen gucken, wie du damit klarkommst. | D11: Speaker 1
A12: 62700 | B12: 69380 | C12: Und dann gibt es jeweils zwei weitere Konversationen und am Ende so eine kleine Fragerunde nochmal. | D12: Speaker 1
A13: 71080 | B13: 78740 | C13: Und genau für die erste Konversation, also diese Warm-Up-Konversation, würde ich die ThinkeLaut-Methode benutzen. | D13: Speaker 1
... A250: 4595880 | B250: 4598820 | C250: Und genau, dann beende ich einmal die Aufnahme. | D250: Speaker 1

Sheet P09
A1: start | B1: end | C1: text | D1: speaker
A2: 1780 | B2: 6280 | C2: Also dann danke dir nochmal, dass du die Zeit genommen hast für die Studie. | D2: Speaker 2
A3: 6940 | B3: 27140 | C3: Die Studie dauert so 45 bis 60 Minuten und das Interview wird aufgezeichnet, um das dann später zu transkribieren und die Aufnahme wird dann nach der Transkription gelöscht und du kannst auch jederzeit das Interview anhalten oder deine Einverständnis erklären, ohne Gründe zu nennen oder irgendwelche Nachteile zu erfahren. | D3: Speaker 2
A4: 27920 | B4: 30220 | C4: Deswegen einmal die Frage, ob du damit einverstanden bist. | D4: Speaker 2
A5: 31240 | B5: 32360 | C5: Ich bin da einverstanden. | D5: Speaker 1
A6: 33100 | B6: 33960 | C6: Okay, perfekt. | D6: Speaker 2
A7: 34760 | B7: 36820 | C7: Genau, dann nochmal kurz zur Struktur. | D7: Speaker 2
A8: 37540 | B8: 42000 | C8: Also im Zuge der Masterarbeit habe ich eine Sprachlern-App gebaut und... | D8: Speaker 2
A9: 42660 | B9: 42800 | C9: Habdino. | D9: Speaker 2
A10: 44280 | B10: 51040 | C10: Also nicht Habdino, sondern nochmal was losgelöst davon und das ist dann eher so aufgebaut wie so ein MVP, sage ich mal. | D10: Speaker 2
A11: 52400 | B11: 58700 | C11: Und das ist der eine Link, den ich dir geschickt habe, das würde eben so aussehen, dass du ein kleines Onboarding machst. | D11: Speaker 2
A12: 60100 | B12: 67700 | C12: Dann hast du drei Konversationen mit einem KI-Partner und zwar eine ist die erste, so eine Warm-up-Konversation. | D12: Speaker 2
A13: 67860 | B13: 80200 | C13: Das heißt, du kannst einfach ganz locker mit dem Reden erstmal so ein bisschen dich zurechtfinden in der App und dann hast du zwei weitere Konversationen und am Ende stelle ich dir noch ein paar Fragen. | D13: Speaker 2
... A866: 4015950 | B866: 4016750 | C866: Dann beende ich einmal die | D866: Speaker 2

Sheet P08
A1: start | B1: end | C1: text | D1: speaker
A2: 870 | B2: 1350 | C2: Genau. | D2: Speaker 1
A3: 3390 | B3: 3870 | C3: Perfekt. | D3: Speaker 1
A4: 6420 | B4: 6840 | C4: Okay, super. | D4: Speaker 1
A5: 7440 | B5: 8600 | C5: Ganz kurz noch dazu. | D5: Speaker 1
A6: 9460 | B6: 14600 | C6: Also einmal, ich habe hier so ein kleines Skript vorbereitet und ich schreibe dann einfach mit. | D6: Speaker 1
A7: 14780 | B7: 17680 | C7: Also nicht, dass du dich wunderst, wenn ich hier mal so ein bisschen tippe. | D7: Speaker 1
A8: 19000 | B8: 22200 | C8: Dann erstmal danke dir, dass du dir die Zeit genommen hast. | D8: Speaker 1
A9: 22840 | B9: 25660 | C9: Und die Studie dauert so ungefähr 45 bis 60 Minuten. | D9: Speaker 1
A10: 26360 | B10: 30060 | C10: Und das Interview wird aufgezeichnet, um das dann später zu transkribieren. | D10: Speaker 1
A11: 30060 | B11: 33720 | C11: Die Audio wird auch dann nach der Transkription gelöscht. | D11: Speaker 1
A12: 34140 | B12: 41040 | C12: Und du kannst auch jederzeit das Interview anhalten oder deine Einverständnis entziehen, ohne irgendwelche Gründe zu nennen oder Nachteile zu bekommen. | D12: Speaker 1
A13: 41580 | B13: 43680 | C13: Deswegen einmal die Frage, ob du damit einverstanden bist. | D13: Speaker 1
... A743: 3879110 | B743: 3880770 | C743: Ich beende mal kurz die Aufnahme. | D743: Speaker 1

Sheet P07
A1: start | B1: end | C1: text | D1: speaker
A2: 0 | B2: 7690 | C2: ...einmal die Aufnahme und ich wollte noch fragen, ob du deinen Bildschirm teilen kannst, dann schicke ich dir gleich die... | D2: Speaker 2
A3: 8850 | B3: 11010 | C3: Äh, geht das denn noch mal? | D3: Speaker 1
A4: 11370 | B4: 12110 | C4: Warte... | D4: Speaker 1
A5: 12110 | B5: 13770 | C5: Was ist bei den Teilen? | D5: Speaker 1
A6: 16450 | B6: 17190 | C6: Äh... | D6: Speaker 1
A7: 17190 | B7: 18190 | C7: Äh... | D7: Speaker 1
A8: 18190 | B8: 20570 | C8: Das hier... | D8: Speaker 1
A9: 20570 | B9: 22210 | C9: Bildschirm teilen, ah! | D9: Speaker 1
A10: 23590 | B10: 26710 | C10: Bildschirm mit Audio teilen... | D10: Speaker 1
A11: 27650 | B11: 28050 | C11: Hm... | D11: Speaker 1
A12: 33890 | B12: 34290 | C12: Hm... | D12: Speaker 1
A13: 36570 | B13: 36970 | C13: Äh... | D13: Speaker 1
... A698: 6354170 | B698: 6358950 | C698: Okay, dann danke dir für deine Teilnahme und ich beende einmal die Aufnahme. | D698: Speaker 2

Sheet P06
A1: start | B1: end | C1: text | D1: speaker
A2: 1930 | B2: 2510 | C2: Genau. | D2: Speaker 1
A3: 3330 | B3: 7450 | C3: Okay, ja dann, also danke dir nochmal, dass du dir die Zeit genommen hast. | D3: Speaker 1
A4: 8370 | B4: 8590 | C4: Gerne. | D4: Speaker 2
A5: 8930 | B5: 27770 | C5: Der User-Test dauert so ungefähr 45 bis 60 Minuten und das Interview wird aufgezeichnet, um das dann später zu transkribieren und die Audio wird dann auch nach der Transkription gelöfft und du kannst auch jederzeit das Interview anhalten oder deine Einwilligung entziehen, ohne Gründe zu nennen oder irgendwelche Nachteile zu bekommen. | D5: Speaker 1
A6: 28270 | B6: 30570 | C6: Deswegen einmal die Frage, ob du damit einverstanden bist. | D6: Speaker 1
A7: 30570 | B7: 31430 | C7: Na klar. | D7: Speaker 1
A8: 32430 | B8: 32970 | C8: Perfekt. | D8: Speaker 1
A9: 33550 | B9: 34130 | C9: Okay, super. | D9: Speaker 1
A10: 34890 | B10: 36590 | C10: Genau, dann einmal zur Struktur. | D10: Speaker 1
A11: 36850 | B11: 38910 | C11: Also ich schicke dir gleich zwei Links. | D11: Speaker 1
A12: 39330 | B12: 44130 | C12: Der eine Link ist für die App und der andere Link ist für den Fragebogen. | D12: Speaker 1
A13: 45390 | B13: 49390 | C13: Und wenn du dann die App startest, hast du erstmal ein kurzes Onboarding. | D13: Speaker 1
... A857: 5209170 | B857: 5210770 | C857: Dann beende ich einmal die auf. | D857: Speaker 1

Sheet P05
A1: start | B1: end | C1: text | D1: speaker
A2: 650 | B2: 1190 | C2: Genau. | D2: Speaker 2
A3: 2430 | B3: 8110 | C3: Und ich habe hier so ein kleines Skript und ich würde nebenbei einfach schreiben. | D3: Speaker 2
A4: 8250 | B4: 14630 | C4: Also nicht, dass du dich wunderst, falls ich mal hier so ein bisschen nach links gucke oder nach rechts bei dir vielleicht. | D4: Speaker 2
A5: 15810 | B5: 21010 | C5: Ja, dann erst mal danke dir nochmal, dass du dir die Zeit genommen hast. | D5: Speaker 2
A6: 21270 | B6: 24490 | C6: Und das Interview dauert so 45 bis 60 Minuten. | D6: Speaker 2
A7: 25530 | B7: 29510 | C7: Und das Interview wird aufgezeichnet mit OBS, um das dann nachher zu transkribieren. | D7: Speaker 2
A8: 30090 | B8: 32810 | C8: Und die Aufzeichnung wird dann nach der Transkription gelöscht. | D8: Speaker 2
A9: 33230 | B9: 41910 | C9: Du kannst auch jederzeit das Interview stoppen oder deine Einverständniserklärung entziehen, ohne Gründe zu nennen oder irgendwelche Nachteile zu erfahren. | D9: Speaker 2
A10: 42470 | B10: 44910 | C10: Deswegen einmal die Frage, ob du damit einverstanden bist. | D10: Speaker 2
A11: 46390 | B11: 47050 | C11: Ja, bin ich. | D11: Speaker 1
A12: 47750 | B12: 48330 | C12: Okay, super. | D12: Speaker 2
A13: 48950 | B13: 52250 | C13: Genau, dann vielleicht kurz nochmal die Struktur. | D13: Speaker 2
... A445: 4029190 | B445: 4034510 | C445: Ähm, ja, dann danke dir auf jeden Fall für die Teilnahme und ich beende einmal kurz die Aufnahme. | D445: Speaker 2

Sheet P04
A1: start | B1: end | C1: text | D1: speaker
A2: 260 | B2: 960 | C2: Ja. | D2: Speaker 2
A3: 1640 | B3: 2000 | C3: Genau. | D3: Speaker 1
A4: 2420 | B4: 6460 | C4: Und dann, also nicht, dass du dich wunderst, ich schreibe hier dann manchmal so ein bisschen mit. | D4: Speaker 1
A5: 8920 | B5: 9440 | C5: Genau. | D5: Speaker 1
A6: 9840 | B6: 12220 | C6: Aber ich, genau, starten wir einfach rein. | D6: Speaker 1
A7: 12340 | B7: 18640 | C7: Also danke dir nochmal für die Teilnahme und die Nutzerstudie dauert so ungefähr 45 bis 60 Minuten. | D7: Speaker 1
A8: 19580 | B8: 27560 | C8: Das Interview wird aufgezeichnet, um das dann später zu transkribieren und die Aufnahme wird dann nach der Transkription gelöscht. | D8: Speaker 1
A9: 27560 | B9: 34620 | C9: Du kannst auch jederzeit das Interview anhalten oder deine Einwilligung entziehen, ohne irgendwelche Gründe zu nennen. | D9: Speaker 1
A10: 35440 | B10: 38080 | C10: Deswegen einmal die Frage, ob du damit einverstanden bist. | D10: Speaker 1
A11: 39520 | B11: 41060 | C11: Ja, ich bin damit einverstanden. | D11: Speaker 2
A12: 41560 | B12: 42160 | C12: Okay, super. | D12: Speaker 1
A13: 42820 | B13: 45700 | C13: Genau, dann nochmal eine kurze Erklärung zur Struktur. | D13: Speaker 1
... A396: 4068310 | B396: 4073610 | C396: Dann danke dir für deine Teilnahme und ich beende einmal die Audio. | D396: Speaker 1

Sheet P03
A1: start | B1: end | C1: text | D1: speaker
A2: 970 | B2: 1510 | C2: Genau. | D2: Speaker 2
A3: 2070 | B3: 3970 | C3: Sag gerne noch mal kurz was, dann … | D3: Speaker 2
A4: 5050 | B4: 5890 | C4: Ja, hallo. | D4: Speaker 2
A5: 6550 | B5: 7570 | C5: Okay, super, ja, perfekt. | D5: Speaker 2
A6: 9670 | B6: 13250 | C6: Genau, ja, dann danke dir erstmal, dass du dir die Zeit heute genommen hast. | D6: Speaker 2
A7: 14450 | B7: 14750 | C7: Gerne. | D7: Speaker 1
A8: 15910 | B8: 16390 | C8: Super. | D8: Speaker 2
A9: 17010 | B9: 20490 | C9: Die User Study dauert so ungefähr 45 bis 60 Minuten. | D9: Speaker 2
A10: 21270 | B10: 25290 | C10: Und das Interview wird aufgezeichnet, um das dann später zu transkribieren. | D10: Speaker 2
A11: 25770 | B11: 29550 | C11: Und die Aufzeichnung wird dann auch nach der Transkription gelöscht. | D11: Speaker 2
A12: 29550 | B12: 38270 | C12: Und du kannst auch jederzeit das Interview anhalten oder deine Einwilligung entziehen, ohne irgendwelche Gründe zu nennen oder irgendwelche Nachteile zu erfahren. | D12: Speaker 2
A13: 38810 | B13: 41110 | C13: Deswegen einmal die Frage, ob du damit einverstanden bist. | D13: Speaker 2
... A579: 4483100 | B579: 4488400 | C579: Dann danke dir auf jeden Fall für deine Teilnahme und dann würde ich einmal die Aufnahme beenden. | D579: Speaker 2

Sheet P02
A1: start | B1: end | C1: text | D1: speaker
A2: 70 | B2: 1350 | C2: Damit bin ich fein. | D2: Speaker 1
A3: 2090 | B3: 2830 | C3: Okay, perfekt. | D3: Speaker 1
A4: 3510 | B4: 3730 | C4: Genau. | D4: Speaker 1
A5: 3910 | B5: 5850 | C5: Dann nochmal danke dir, dass du dir die Zeit nimmst. | D5: Speaker 1
A6: 5930 | B6: 8950 | C6: Also die Studie dauert so ungefähr 45 bis 60 Minuten. | D6: Speaker 1
A7: 9950 | B7: 15450 | C7: Und das Interview wird mit OBS aufgezeichnet, um das dann später zu transkribieren. | D7: Speaker 1
A8: 15990 | B8: 18170 | C8: Die Audio wird dann nach der Transkription gelöscht. | D8: Speaker 1
A9: 18550 | B9: 26210 | C9: Und du kannst auch jederzeit das Interview anhalten oder deine Einwilligung quasi entziehen, ohne irgendwelche Gründe zu nennen. | D9: Speaker 1
A10: 26830 | B10: 29070 | C10: Deswegen nur einmal die Frage, bist du damit einverstanden? | D10: Speaker 1
A11: 30030 | B11: 31110 | C11: Damit bin ich einverstanden. | D11: Speaker 1
A12: 31509 | B12: 32230 | C12: Okay, super. | D12: Speaker 1
A13: 32750 | B13: 35310 | C13: Dann noch ein paar kleine Infos zur Struktur. | D13: Speaker 1
... A878: 4084920 | B878: 4087280 | C878: Dann beende ich einmal die Aufnahme. | D878: Speaker 1

Sheet P01
A1: Participant ID | B1: start | C1: end | D1: text | E1: speaker
A2: 1 | B2: 1029 | C2: 9370 | D2: Ja, dann nochmal danke dir, dass du dir die Zeit genommen hast und die Nutzerstudie dauert | E2: Speaker 2
A3: 1 | B3: 9370 | C3: 16450 | D3: so ungefähr 45 bis 60 Minuten, das Interview wird mit der Software OBS aufgezeichnet, um | E3: Speaker 2
A4: 1 | B4: 16450 | C4: 22550 | D4: das dann später zu transkribieren und die Audio wird dann nach der Transkription gelöfft | E4: Speaker 2
A5: 1 | B5: 22550 | C5: 28670 | D5: und du kannst auch während des Interviews immer stoppen und deine Einwilligungen zurückziehen | E5: Speaker 2
A6: 1 | B6: 28670 | C6: 35210 | D6: ohne irgendwelche Gründe zu benennen oder negative Folgen davon zu bekommen und deswegen | E6: Speaker 2
A7: 1 | B7: 35210 | C7: 38090 | D7: einmal die Frage, ob du damit einverstanden bist, dass ich das aufzeichne? | E7: Speaker 2
A8: 1 | B8: 39390 | C8: 39550 | D8: Ja. | E8: Speaker 2
A9: 1 | B9: 40250 | C9: 41070 | D9: Okay, perfekt. | E9: Speaker 2
A10: 1 | B10: 42690 | C10: 50650 | D10: Und genau, dann einmal zur Struktur, also du hast ja schon den Link bekommen zu der App | E10: Speaker 2
A11: 1 | B11: 51530 | C11: 57910 | D11: und das sieht wie folgendermaßen aus, die Nutzerstudie, zuerst musst du ein kleines Onboarding | E11: Speaker 2
A12: 1 | B12: 57910 | C12: 65030 | D12: machen, um ein paar Fragen zu beantworten, dann hast du eine Konversation als Warm-up | E12: Speaker 2
A13: 1 | B13: 65030 | C13: 70770 | D13: und dann zwei weitere Konversationen und nach jeder Konversation hast du nochmal so eine | E13: Speaker 2
... A907: 1 | B907: 7575360 | C907: 7580380 | D907: Dann danke dir auf jeden Fall für deine Teilnahme und dann beende ich einmal die Aufnahme. | E907: Speaker 2
